Workbook

Sheet Как пользоваться
A1: Реестр источников событий — Кембридж и окрестности (v0.4, сентябрь 2026)
A3: Источники — основная таблица. Одна строка = один источник. Фильтры в заголовке.
A4: Жёлтым выделено: URL не проверен или не указан — нужно найти/подтвердить перед написанием парсера.
A5: «URL проверен = да» — адрес подтверждён поиском; «проверить» — источник известен, но адрес и формат нужно сверить.
A6: Приоритет: 1 — брать в MVP, 2 — вторая волна, 3 — когда будет время.
A7: Способ сбора: RSS / iCal / API — дешёвый и надёжный; HTML — парсинг; Ручной — ежегодные события, проще завести руками.
A8: Сводка — счётчики по категориям (формулы, пересчитываются сами).
A9: Схема события — поля, которые парсер должен заполнять для каждого события.
A10: Категории и теги — справочник значений для полей category и тегов.
A12: Пример строки: S047 Talks.cam — готовые iCal/RSS/XML-фиды с датой, местом и организатором; приоритет 1.
A13: v0.4 (2026-09-27): проверены источники приоритета 1 — см. лист «Проверка P1»; новые столбцы «Endpoint для сбора», «robots.txt», «Проверено». «URL проверен = нет» — URL не отвечает (красный).
A14: v0.4, правки после этапа 1: Eventbrite (S008) поднят до приоритета 1; добавлены S090 DesignMyNight и S091 Cambridge Live Tickets; лист «Контрольные события» (источник — data/control_events.json).
... A20: v0.10 (2026-09-30): этап 7c — Cambridge Union: Varsity (S176) и termcard на Issuu (S177); ссылки S123 и S144 исправлены по проверкам выпуска.

Sheet Источники
A1: ID | B1: Категория | C1: Источник | D1: Тип источника | E1: URL | F1: Что покрывает | G1: Зона | H1: Способ сбора | I1: Частота | J1: Приоритет | K1: URL проверен | L1: Заметки | M1: Endpoint для сбора | N1: robots.txt | O1: Проверено | P1: Партнёрская программа
A2: S001 | B2: Сквозные агрегаторы | C2: Visit Cambridge — events | D2: Агрегатор | E2: https://www.visitcambridge.org | F2: Официальный туристический календарь, все категории | G2: Центр | H2: API + HTML | I2: Ежедневно | J2: 1 | K2: да | L2: Хорошая опорная база, но туристический уклон. v0.4: внутренний API vc-map отдаёт события с адресом и postcode, но без дат — даты брать со страниц /event/… Этап 6: подключён — 7 разделов /event-categories/ (постранично) + страницы событий; раздел family-friendly → категория family | M2: https://www.visitcambridge.org/wp-json/vc-map/v1/events | N2: разрешено | O2: 2026-09-28 | P2: события ведут к: продавец не определён — 17 соб.; Ticket Tailor — 6 соб.: программы нет; DigiTickets — 3 соб.: программа есть
A3: S002 | B3: Сквозные агрегаторы | C3: What's On In Cambridge | D3: Агрегатор | E3: https://www.whatsonincambridge.com/__superjs/challenge?u=%2Fevents%2F | F3: Календарь событий, все категории | G3: Центр | H3: RSS | I3: Ежедневно | J3: 1 | K3: да | L3: Сами предупреждают, что обновляют не каждый день — использовать как подсказку, сверять с первоисточником. v0.4: RSS жив (10 записей); страница /events/ за JS-проверкой | M3: https://www.whatsonincambridge.com/feed/ | N3: разрешено | O3: 2026-09-27
A4: S003 | B4: Сквозные агрегаторы | C4: Cambridge Independent — What's On | D4: СМИ | E4: https://www.cambridgeindependent.co.uk/whats-on/ | F4: Анонсы концертов, театра, кино, семейного | G4: Центр + 30 мин | H4: RSS | I4: Ежедневно | J4: 1 | K4: да | L4: Также спортивный раздел — календари United | M4: https://www.cambridgeindependent.co.uk/_api/rss/cambridge_independent_whatson_feed.xml | N4: разрешено | O4: 2026-09-27 | P4: события ведут к: продавец не определён — 5 соб.; Cambridge Live (касса Corn Exchange и Guildhall) — 2 соб.: программы нет; WeGotTickets — 2 соб.: программа есть
A5: S004 | B5: Сквозные агрегаторы | C5: Cambridge News / CambridgeshireLive | D5: СМИ | E5: https://www.cambridge-news.co.uk | F5: Новости, анонсы, отмены, перекрытия | G5: Центр + час | H5: RSS | I5: 2–3 раза в день | J5: 1 | K5: да | L5: Ключевой источник для контура отмен. v0.4: раздел What's On: /whats-on/?service=rss; общий фид новостей /?service=rss — для контура отмен | M5: https://www.cambridge-news.co.uk/whats-on/?service=rss | N5: разрешено | O5: 2026-09-27 | P5: события ведут к: продавец не определён — 2 соб.
A6: S005 | B6: Сквозные агрегаторы | C6: Cambridge 105 — события | D6: СМИ / календарь | E6: https://cambridge105.co.uk | F6: Общественное радио, календарь местных событий | G6: Центр | H6: iCal | I6: Ежедневно | J6: 1 | K6: да | L6: Поймал Thriplow Daffodil Weekend — сильный источник по деревенскому long tail. v0.4: iCal The Events Calendar (22 события) + REST /wp-json/tribe/events/v1/events | M6: https://cambridge105.co.uk/whatson/?ical=1 | N6: разрешено | O6: 2026-09-27 | P6: события ведут к: продавец не определён — 10 соб.; Spektrix (касса площадки) — 1 соб.: программы нет; Cambridge Live (касса Corn Exchange и Guildhall) — 1 соб.: программы нет
A7: S006 | B7: Сквозные агрегаторы | C7: Ents24 — Cambridge | D7: Агрегатор | E7: https://www.ents24.com/whatson/cambridge | F7: Концерты, комедия, театр по всем площадкам | G7: Центр + 30 мин | H7: JSON-LD | I7: Ежедневно | J7: 1 | K7: да | L7: Удобно ловить объявления новых шоу. v0.4: JSON-LD на первой странице списка (~37 событий), продолжение подгружается JS; через Ents24 ловим и Arts Theatre (S041) | M7: https://www.ents24.com/whatson/cambridge | N7: разрешено | O7: 2026-09-27 | P7: события ведут к: Cambridge Live (касса Corn Exchange и Guildhall) — 1 соб.: программы нет
A8: S007 | B8: Сквозные агрегаторы | C8: Skiddle — Cambridge | D8: Агрегатор / билеты | E8: https://www.skiddle.com/whats-on/Cambridge/ | F8: Клубы, гиги, фестивали | G8: Центр | H8: JSON-LD | I8: Ежедневно | J8: 1 | K8: да | L8: Есть API и партнёрка — сразу и данные, и монетизация. v0.4: ~49 событий JSON-LD на первой странице списка; продолжение подгружается JS; API и ключ не нужны (решение после этапа 1) | M8: https://www.skiddle.com/whats-on/Cambridge/ | N8: разрешено | O8: 2026-09-27 | P8: Skiddle: есть — Skiddle Ticket Affiliate Programme (своя)
A9: S008 | B9: Сквозные агрегаторы | C9: Eventbrite — Cambridge | D9: Агрегатор / билеты | E9: https://www.eventbrite.co.uk/d/united-kingdom--cambridge/all-events/ | F9: Воркшопы, лекции, нетворкинг, благотворительность | G9: Центр + 30 мин | H9: JSON-LD | I9: Ежедневно | J9: 1 | K9: да | L9: Много шума — нужен жёсткий фильтр. v0.4: поднят до P1 в v0.4; 20 событий JSON-LD на страницу, с postcode и координатами; фильтр — почтовые области CB, PE, SG, CM, IP, онлайн отбрасываем | M9: https://www.eventbrite.co.uk/d/united-kingdom--cambridge/all-events/?page=N | N9: разрешено | O9: 2026-09-27 | P9: Eventbrite: есть — Eventbrite Affiliate Program (в условиях не указана (обзоры: impact.com))
A10: S009 | B10: Сквозные агрегаторы | C10: Songkick — площадки Кембриджа | D10: Агрегатор | E10: https://www.songkick.com | F10: Концерты по площадкам | G10: Центр | H10: HTML (API для новых партнёров ограничен — проверить) | I10: Еженедельно | J10: 3 | K10: да | L10: Этап 6: не нужен — Songkick: страница города — 404, API для новых партнёров закрыт; концерты покрыты Ents24/Skiddle (S006, S007) | O10: 2026-09-28
A11: S010 | B11: Сквозные агрегаторы | C11: Peterborough Telegraph | D11: СМИ | E11: https://www.peterboroughtoday.co.uk | F11: Север графства: Уиттлси, Питерборо, фены | G11: Час | H11: RSS (уточнить) | I11: Ежедневно | J11: 2 | K11: да | L11: Этап 5: подключён — RSS (HTML сайта — 403); статьи → извлечение через Claude | M11: https://www.peterboroughtoday.co.uk/rss | N11: разрешено | O11: 2026-09-28
A12: S011 | B12: Концерты | C12: Cambridge Corn Exchange | D12: Площадка | E12: https://www.cornex.co.uk/events | F12: Крупные концерты, комедия, балет, городские события | G12: Центр | H12: HTML + JSON-LD | I12: Ежедневно | J12: 1 | K12: да | L12: Сайт Cambridge Live — там же городские события (фейерверки и др.). v0.4: сайт Corn Exchange — cornex.co.uk; список в HTML, на странице события JSON-LD Event с адресом и postcode; cambridgelive.org.uk → билетный сайт | M12: https://www.cornex.co.uk/events | N12: разрешено | O12: 2026-09-27 | P12: события ведут к: Cambridge Live (касса Corn Exchange и Guildhall) — 10 соб.: программы нет
A13: S012 | B13: Концерты | C13: Cambridge Junction | D13: Площадка | E13: https://www.junction.co.uk | F13: Концерты, комедия, клубные вечера, театр | G13: Центр | H13: API + HTML | I13: Ежедневно | J13: 1 | K13: да | L13: v0.4: WP REST, тип cj_events: названия и ссылки, дат нет — даты со страниц; /feed/ — это блог, не афиша Этап 6: подключён — HTML /whats-on/page/N + страницы событий («Event Information»: дата, время, цена); кэш страниц | M13: https://www.junction.co.uk/wp-json/wp/v2/cj_events | N13: разрешено | O13: 2026-09-28 | P13: события ведут к: Spektrix (касса площадки) — 24 соб.: программы нет; Eventbrite — 1 соб.: программа есть; Ticket Tailor — 1 соб.: программы нет
A14: S013 | B14: Концерты | C14: The Portland Arms | D14: Площадка | F14: Небольшие рок/инди-концерты | G14: Центр | H14: Через Ents24/Skiddle | I14: Еженедельно | J14: 2 | K14: нет | L14: Этап 5: не нужен — robots.txt отвечает 403; концерты есть на Ents24/Skiddle (S006/S007) | N14: — | O14: 2026-09-28
A15: S014 | B15: Концерты | C15: Storey's Field Centre (Eddington) | D15: Площадка | F15: Камерная музыка, фолк, джаз | G15: Центр | H15: HTML | I15: Еженедельно | J15: 2 | K15: да | L15: Этап 5: не нужен — фид — 3 новости; события продаются через Eventbrite (S008) и Cambridge Live Tickets (S091) | M15: https://www.storeysfieldcentre.org.uk/feed/ | N15: разрешено | O15: 2026-09-28
A16: S015 | B16: Концерты | C16: West Road Concert Hall | D16: Площадка | F16: Классика, университетские оркестры | G16: Центр | H16: HTML | I16: Еженедельно | J16: 2 | K16: да | L16: Этап 5: не нужен — HTML без JSON-LD; концерты уже приходят из S091, S005, S007, S008 | M16: https://www.westroad.org | N16: разрешено | O16: 2026-09-28
A17: S016 | B17: Концерты | C17: Хоровая музыка колледжей (King's, St John's, Trinity) | D17: Площадка | F17: Evensong, концерты хоров, органные вечера | G17: Центр | H17: HTML по колледжам | I17: Еженедельно | J17: 3 | K17: — | L17: Бесплатно — хороший материал для рубрики «бесплатно» Этап 6: не нужен — хоровая музыка колледжей — покрыто: King's/GSM через Ents24 и University What's On (S048), St John's/Trinity — Visit Cambridge (S001); регулярный evensong в выпуск не идёт | O17: 2026-09-28
A18: S017 | B18: Концерты | C18: Saffron Hall | D18: Площадка | F18: Классика и крупные концерты | G18: Час | H18: HTML | I18: Еженедельно | J18: 2 | K18: да | L18: Этап 5: подключён — HTML-карточки: дата, время, наличие билетов (Nearly full → «мало билетов»), отмены | M18: https://www.saffronhall.com/ | N18: разрешено | O18: 2026-09-28 | P18: события ведут к: Spektrix (касса площадки) — 7 соб.: программы нет
A19: S018 | B19: Спорт — смотреть | C19: Cambridge United | D19: Клуб | E19: https://www.cambridgeunited.com/fixture/list/57 | F19: Матчи Лиги 1, кубки | G19: Центр | H19: iCal (fixtur.es) + HTML | I19: Еженедельно | J19: 1 | K19: да | L19: Календарь сезона публикуется летом целиком. v0.4: у клуба календарь только в HTML (/fixture/list/57); готовый iCal домашних матчей — сторонний fixtur.es, сверять с сайтом клуба | M19: https://ics.fixtur.es/v2/home/cambridge-united-fc.ics | N19: разрешено | O19: 2026-09-27 | P19: события ведут к: своя касса (cambridgeunited.com) — 2 соб.: программы нет
A20: S019 | B20: Спорт — смотреть | C20: Cambridge City FC | D20: Клуб | F20: Нон-лиг футбол | G20: 30 мин | H20: HTML | I20: Еженедельно | J20: 3 | K20: да | L20: Этап 6: не нужен — Cambridge City FC: 8-й уровень (Isthmian North, стадион в Sawston), матчи низкой значимости; сайт лиги без календаря в HTML, Football Web Pages — 403 Этап 6c: подключён — Cambridge City FC: домашние матчи из событий сайта клуба (Wix) → «Спорт → Также играют» Ошибочное прежнее решение: S019 (этап 6: «не нужен, матчи низкой значимости») — отменено владельцем проекта после v5. | O20: 2026-09-29 | P20: события ведут к: своя касса (cambridgecityfc.com) — 1 соб.: программы нет
A21: S020 | B21: Спорт — смотреть | C21: Cambridge Rugby Club | D21: Клуб | F21: Регби, National League | G21: Центр | H21: HTML | I21: Еженедельно | J21: 2 | K21: нет | L21: Этап 5: закрыт — страница-проверка (HTTP 202, бот-защита); обходить не будем Этап 6c: подключён — Cambridge RUFC: сайт клуба за бот-защитой; с 2026/27 — National League 1 (выбыли из Champ Rugby), весь сезон — PDF лиги (nationalleaguerugby.com) Ошибочное прежнее решение: S020 (этап 5: «закрыт — бот-защита») — календарь нашёлся на сайте лиги. | N21: — | O21: 2026-09-29 | P21: события ведут к: продавец не определён — 1 соб.
A22: S021 | B22: Спорт — смотреть | C22: Newmarket Racecourses | D22: Площадка | E22: https://www.thejockeyclub.co.uk/newmarket/events-tickets/ | F22: Скачки, летние концерты Newmarket Nights | G22: 30 мин | H22: JSON-LD | I22: Еженедельно | J22: 1 | K22: да | L22: Сайт Jockey Club | M22: https://www.thejockeyclub.co.uk/newmarket/events-tickets/ | N22: разрешено | O22: 2026-09-27 | P22: The Jockey Club (Newmarket, Huntingdon): есть — Jockey Club Racecourses (Awin (ID 7677))
A23: S022 | B23: Спорт — смотреть | C23: Huntingdon Racecourse | D23: Площадка | F23: Скачки | G23: 30 мин | H23: HTML | I23: Еженедельно | J23: 3 | K23: да | L23: Сайт Jockey Club Этап 6: подключён — Huntingdon Racecourse: JSON-LD на странице событий Jockey Club (как Newmarket S021) | O23: 2026-09-28 | P23: The Jockey Club (Newmarket, Huntingdon): есть — Jockey Club Racecourses (Awin (ID 7677))
A24: S023 | B24: Спорт — смотреть | C24: CUCBC — May Bumps / Lent Bumps | D24: Организатор | F24: Университетские гонки гребных лодок: Lent Bumps (февраль–март) и May Bumps (июнь) | G24: Центр | H24: HTML | I24: Сезонно | J24: 2 | K24: да | L24: Этап 5: ежегодное — Lent/May Bumps — сезонно; RSS новостей есть; даты — через recurring_events | M24: https://www.cucbc.org/rss.xml | N24: разрешено | O24: 2026-09-28
A25: S024 | B25: Спорт — смотреть | C25: Town Bumps (Cambridgeshire Rowing Association) | D25: Организатор | F25: Городские гонки гребных лодок, лето | G25: Центр | H25: HTML | I25: Сезонно | J25: 3 | K25: нет | L25: Этап 6: ежегодное — Town Bumps: сайт Cambridgeshire Rowing Association отвечает 502; летние Town Bumps — в бэклог recurring (дата вручную) | O25: 2026-09-28
A26: S025 | B26: Спорт — смотреть | C26: Varsity-матчи (Oxford vs Cambridge) | D26: Организатор | F26: Регби, гребля и др. дерби университетов | G26: Центр + Лондон | H26: Ручной (календарь) | I26: Ежегодно | J26: 3 | K26: — | L26: Этап 6: вручную — Varsity-матчи: календарь вручную (даты публикуются университетскими клубами), крупные — через статьи | O26: 2026-09-28
A27: S026 | B27: Спорт — участвовать | C27: Chariots of Fire | D27: Организатор | E27: https://www.chariots-of-fire.co.uk/ | F27: Благотворительная эстафета, сентябрь | G27: Центр | H27: JSON-LD (RunThrough) | I27: Ежегодно | J27: 1 | K27: да | L27: Регистрация через RunThrough. v0.4: ежегодно; JSON-LD Event на странице RunThrough; /feed/ сайта — новости Этап 6: ежегодное — через recurring_events (R11) | M27: https://www.runthrough.co.uk/event/chariots-of-fire-september-2026 | N27: разрешено | O27: 2026-09-28
A28: S027 | B28: Спорт — участвовать | C28: RunThrough — события в Кембридже | D28: Организатор / регистрация | E28: https://www.runthrough.co.uk | F28: Забеги, эстафеты | G28: Центр + 30 мин | H28: HTML | I28: Еженедельно | J28: 2 | K28: да | L28: Этап 5: подключён — JSON-LD SportsEvent, но список — 24 ближайших забега по стране; сейчас в регионе 0 (фильтр по почтовым зонам). Ценность низкая — пересмотреть на этапе 6 | M28: https://www.runthrough.co.uk/events-timeline | N28: разрешено | O28: 2026-09-28
A29: S028 | B29: Спорт — участвовать | C29: Cambridge Half Marathon | D29: Организатор | E29: https://cambridgehalfmarathon.com/ | F29: Полумарафон, март | G29: Центр | H29: HTML | I29: Ежегодно | J29: 1 | K29: да | L29: Важен и для рубрики «Практическое» — перекрытия Этап 6: ежегодное — через recurring_events (R03) | M29: https://cambridgehalfmarathon.com/ | N29: разрешено | O29: 2026-09-28
A30: S029 | B30: Спорт — участвовать | C30: Let's Do This — Cambridgeshire | D30: Агрегатор / регистрация | E30: https://www.letsdothis.com | F30: Забеги, триатлоны, велозаезды | G30: Час | H30: HTML | I30: Еженедельно | J30: 2 | K30: нет | L30: Этап 5: закрыт — robots.txt отвечает 403 | N30: — | O30: 2026-09-28
A31: S030 | B31: Фестивали | C31: Cambridge Festival (университет) | D31: Организатор | E31: https://www.festival.cam.ac.uk/events | F31: Наука, гуманитарные темы, весна | G31: Центр | H31: HTML (curl, пауза 10 с) | I31: Сезонно | J31: 1 | K31: да | L31: v0.4: решение после этапа 1: собирать через curl с честным User-Agent и паузой 10 с (robots.txt разрешает, Crawl-delay 10); под браузер не маскироваться; фестиваль в марте Этап 6: ежегодное — Cambridge Festival — весна; дата через recurring_events (R04); коллектор программы — перед фестивалем (март) | M31: https://www.festival.cam.ac.uk/events | N31: разрешено, Crawl-delay 10 | O31: 2026-09-28
A32: S031 | B32: Фестивали | C32: Cambridge Folk Festival | D32: Организатор | E32: https://www.cambridgefolkfestival.co.uk/ | F32: Фолк-фестиваль, лето | G32: Центр | H32: HTML | I32: Ежегодно | J32: 1 | K32: да | L32: v0.4: ежегодно; cambridgelive.org.uk/folk-festival → cambridgefolkfestival.co.uk Этап 6: ежегодное — через recurring_events (R09) | M32: https://www.cambridgefolkfestival.co.uk/ | N32: разрешено | O32: 2026-09-28
A33: S032 | B33: Фестивали | C33: Cambridge Beer Festival | D33: Организатор | E33: https://www.cambridgebeerfestival.com | F33: Пивной фестиваль CAMRA, май | G33: Центр | H33: iCal | I33: Ежегодно | J33: 1 | K33: да | M33: https://www.cambridgebeerfestival.com/events/?ical=1 | N33: разрешено | O33: 2026-09-27 | P33: события ведут к: продавец не определён — 1 соб.
A34: S033 | B34: Фестивали | C34: Strawberry Fair | D34: Организатор | E34: https://strawberry-fair.org.uk/ | F34: Бесплатный фестиваль на Midsummer Common, июнь | G34: Центр | H34: JSON-LD | I34: Ежегодно | J34: 1 | K34: да | L34: Бывали отмены — мониторить. v0.4: JSON-LD Event на главной; /feed/ отдаёт HTML, фида нет | M34: https://strawberry-fair.org.uk/ | N34: разрешено | O34: 2026-09-27
A35: S034 | B35: Фестивали | C35: Whittlesea Straw Bear Festival | D35: Организатор | F35: Средневековый зимний фестиваль, январь | G35: Час | H35: Ручной + Peterborough Telegraph | I35: Ежегодно | J35: 2 | K35: да | L35: Этап 5: ежегодное — уже в recurring_events (R01) | M35: https://www.strawbear.org.uk | N35: разрешено | O35: 2026-09-28
A36: S035 | B36: Фестивали | C36: Cambridge Film Festival | D36: Организатор | F36: Кинофестиваль, осень | G36: Центр | H36: Ручной (ежегодно) | I36: Ежегодно | J36: 2 | K36: да | L36: Этап 5: ежегодное — фестиваль раз в год (осень); HTML без фида — предлагаю добавить в recurring_events | M36: https://www.cambridgefilmfestival.org.uk | N36: разрешено | O36: 2026-09-28
A37: S036 | B37: Фестивали | C37: Cambridge Literary Festival | D37: Организатор | F37: Литфестиваль, весна и осень | G37: Центр | H37: HTML | I37: Сезонно | J37: 2 | K37: нет | L37: Этап 5: закрыт — 403 на сайт и /events | N37: — | O37: 2026-09-28
A38: S037 | B38: Фестивали | C38: Cambridge Science Festival / семейные программы | D38: Организатор | F38: См. Cambridge Festival | G38: Центр | H38: — | I38: — | J38: 3 | K38: — | L38: Дубль — проверить, не слит ли с Cambridge Festival Этап 6: не нужен — Cambridge Science Festival слит с Cambridge Festival — дубль R04 | O38: 2026-09-28
A39: S038 | B39: Ярмарки | C39: Mill Road Winter Fair | D39: Организатор | E39: https://www.millroadwinterfair.org | F39: Уличная ярмарка, первая суббота декабря; Mill Road Fringe в течение года | G39: Центр | H39: RSS | I39: Еженедельно в сезон | J39: 1 | K39: да | L39: Отмены публикуются в соцсетях — нужен контур отмен. v0.4: RSS — новости ярмарки; дату (5.12.2026) и отмены сверять по главной | M39: https://www.millroadwinterfair.org/feed/ | N39: разрешено | O39: 2026-09-27 | P39: события ведут к: продавец не определён — 1 соб.
A40: S039 | B40: Ярмарки | C40: Рождественские маркеты в центре | D40: Организатор | E40: https://www.christmasincambridge.co.uk/ | F40: Сезонные рынки | G40: Центр | H40: HTML | I40: Сезонно | J40: 1 | K40: да | L40: v0.4: сезонно (ноябрь–декабрь); фидов нет Этап 6: ежегодное — Christmas in Cambridge (Parker's Piece: каток, маркет, колесо) — recurring R21, дата со страницы (13.11.2026 – 3.01.2027) | M40: https://www.christmasincambridge.co.uk/ | N40: разрешено | O40: 2026-09-28
A41: S040 | B41: Ярмарки | C41: Деревенские fetes и летние ярмарки | D41: Организатор | F41: Village fetes вокруг Кембриджа | G41: 30 мин | H41: Eventbrite / Visit Cambridge / FB-группы вручную | I41: Сезонно | J41: 3 | K41: — | L41: Трудно собрать автоматически Этап 6: покрыт — деревенские fetes — через Eventbrite (S008), Visit Cambridge (S001), статьи Newsquest (S116–S119); Facebook-группы не парсим | O41: 2026-09-28
A42: S041 | B42: Театр | C42: Cambridge Arts Theatre | D42: Площадка | E42: https://www.artstheatre.co.uk | F42: Драма, мюзиклы, пантомима | G42: Центр | H42: Через Ents24 (S006) | I42: Ежедневно | J42: 1 | K42: нет | L42: v0.4: решение после этапа 1: защиту не обходим; афишу Arts Theatre берём из Ents24. Домен: cambridgeartstheatre.com → artstheatre.co.uk Этап 6: покрыт — защита от ботов; афиша — через Ents24 (S006) | N42: разрешено | O42: 2026-09-28
A43: S042 | B43: Театр | C43: ADC Theatre | D43: Площадка | E43: https://www.adctheatre.com | F43: Студенческий театр, комедия (Footlights) | G43: Центр | H43: iCal | I43: Еженедельно | J43: 1 | K43: да | L43: Дёшево и часто — хорош для рубрики «недорого». v0.4: афиша ADC ведётся в Camdram: iCal /venues/adc-theatre/diary.ics и JSON diary.json; билеты — Spektrix Этап 6c: подключён — ADC Theatre: цены — со страницы продажи adctheatre.com (robots.txt отвечает 404 — правил нет) | M43: https://www.camdram.net/venues/adc-theatre/diary.ics | N43: разрешено | O43: 2026-09-29 | P43: события ведут к: Spektrix (касса площадки) — 4 соб.: программы нет; продавец не определён — 1 соб.
A44: S043 | B44: Театр | C44: Mumford Theatre (ARU) | D44: Площадка | F44: Любительский и гастрольный театр | G44: Центр | H44: HTML | I44: Еженедельно | J44: 3 | K44: да | L44: Этап 6: подключён — Mumford Theatre (ARU): афиша на Eventbrite (страница организатора), JSON-LD страниц событий; сейчас у организатора 0 предстоящих (upcomingEventsTotal: 0) — межсезонье | O44: 2026-09-28
A45: S044 | B45: Театр | C45: Постановки в садах колледжей (лето) | D45: Организатор | F45: Шекспир под открытым небом | G45: Центр | H45: Ручной | I45: Сезонно | J45: 2 | K45: да | L45: Этап 5: ежегодное — летний сезон постановок; ручной сезонный календарь | M45: https://cambridgeshakespeare.com/ | N45: разрешено | O45: 2026-09-28
A46: S045 | B46: Кино | C46: Arts Picturehouse | D46: Площадка | E46: https://www.picturehouses.com/cinema/arts-picturehouse-cambridge | F46: Арт-кино, спецпоказы, Q&A | G46: Центр | H46: HTML | I46: Еженедельно | J46: 1 | K46: да | L46: Этап 6: не нужен — сеансы — только через внутренний AJAX с XSRF-токеном сессии (не используем); обычные сеансы — не события выпуска; спецпоказы приходят через Visit Cambridge, статьи и Cambridge Film Festival (recurring R17) Этап 6c: подключён — Arts Picturehouse: страница кинотеатра без AJAX — спецпоказы с датой и «Now Playing»; сеансы (AJAX с XSRF-токеном) не используем Ошибочное прежнее решение: S045 (этап 6: «не нужен») — ошибочно: для рубрики «В кино» нужны спецпоказы и новые фильмы, а не сеансы. | M46: https://www.picturehouses.com/cinema/arts-picturehouse-cambridge | N46: разрешено | O46: 2026-09-29 | P46: события ведут к: продавец не определён — 5 соб.
A47: S046 | B47: Кино | C47: Кино под открытым небом (летние сезоны) | D47: Организатор | F47: Летние показы в парках и колледжах | G47: Центр | H47: Ручной | I47: Сезонно | J47: 2 | K47: нет событий | L47: Этап 5: ежегодное — летние показы; адрес организатора не подтверждён — ручной сезонный | M47: https://www.cambridgefilmfestival.org.uk | N47: разрешено | O47: 2026-09-28
A48: S047 | B48: Лекции | C48: Talks.cam | D48: Календарь | E48: https://talks.cam.ac.uk | F48: Университетские лекции и семинары; есть публичные списки | G48: Центр | H48: iCal | I48: Ежедневно | J48: 1 | K48: да | L48: Лучший технический источник: готовые фиды с датой, местом и организатором. v0.4: 5 публичных списков: 5606 Featured talks, 5462 Major Public Lectures in Cambridge, 5358 Darwin College Lecture Series, 5769 Cabinet of Natural History, 23088 CamTalks; список Fitzwilliam (12614) пуст; фиды /show/ics|rss|xml/<id> | M48: https://talks.cam.ac.uk/show/ics/{5606,5462,5358,5769,23088}/ | N48: разрешено | O48: 2026-09-27 | P48: события ведут к: продавец не определён — 3 соб.
A49: S048 | B49: Лекции | C49: University of Cambridge — What's On | D49: Календарь | E49: https://www.admin.cam.ac.uk/whatson/ | F49: Публичные события университета | G49: Центр | H49: HTML | I49: Еженедельно | J49: 1 | K49: да | L49: v0.4: решение после этапа 1: уважаем Disallow на webservices.admin.cam.ac.uk; собираем HTML-страницу admin.cam.ac.uk/whatson/ (robots.txt её разрешает); лекции также покрывает talks.cam Этап 6: подключён — недельные страницы admin.cam.ac.uk/whatson (3 недели) + раздел Families; iCal/RSS на webservices закрыты robots.txt — не используем | M49: https://www.admin.cam.ac.uk/whatson/ | N49: разрешено (страница); фиды — запрещено | O49: 2026-09-28 | P49: события ведут к: продавец не определён — 24 соб.; Eventbrite — 2 соб.: программа есть; DigiTickets — 1 соб.: программа есть
A50: S049 | B50: Лекции | C50: Cambridge Union | D50: Организатор | E50: https://cus.org/event | F50: Дебаты и выступления известных гостей | G50: Центр | H50: JSON (WordPress REST) + страница события | I50: Ежедневно | J50: 2 | K50: да | L50: Этап 5: не нужен — мероприятия в основном для членов Union; публичные крупные гости попадают в новости Этап 7b: подключён — события EventJet — записи WordPress event_jet (открытый REST, без токенов); уровень доступа и площадка — со страницы события, дата и цена — Haiku. Доступ: Open To The Public / Ticketed — для всех; Members Only, Members & Cambridge Students — «только для членов», членство Open для всех £370 в год; Life/Annual/Access, Students, Staff — не берём. Termcard — Issuu (картинки), не разбираем. На 30.09 опубликованных событий 0 (Michaelmas не выложен). cus.org отвечает 429 — пауза 10 с. The Orator's Cellar на Skiddle — «No events to display»; площадки The Orator / The Footlight Cellars склеиваются синонимами. Этап 7c: на cus.org/event клуб публикует только билетные мероприятия (ужины, вечеринки в The Orator); программа гостей и дебатов — termcard (S177) и статьи Varsity (S176). В выпуске — одна строка «В Cambridge Union на этой неделе (для членов клуба): …»; открытые для всех — обычными пунктами после появления на cus.org. | M50: https://cus.org/wp-json/wp/v2/event_jet | N50: разрешено | O50: 2026-09-30
A51: S050 | B51: Выставки и музеи | C51: Fitzwilliam Museum | D51: Площадка | E51: https://fitzmuseum.cam.ac.uk/events | F51: Выставки, лекции, семейные программы | G51: Центр | H51: RSS (выставки) + HTML (события) | I51: Еженедельно | J51: 1 | K51: да | L51: v0.4: Atom-фид выставок (20 записей); события — HTML /events; /whats-on — 404 | M51: https://fitzmuseum.cam.ac.uk/feeds/exhibitions | N51: разрешено | O51: 2026-09-27 | P51: события ведут к: продавец не определён — 2 соб.
A52: S051 | B52: Выставки и музеи | C52: Kettle's Yard | D52: Площадка | E52: https://www.kettlesyard.cam.ac.uk/whats-on/ | F52: Современное искусство, концерты, воркшопы | G52: Центр | H52: HTML | I52: Еженедельно | J52: 1 | K52: да | L52: Этап 5: подключён — приоритет 1, коллектора не было: HTML страниц событий (контрольный пример этапа 5) | M52: https://www.kettlesyard.cam.ac.uk/whats-on/ | N52: разрешено | O52: 2026-09-28 | P52: события ведут к: DigiTickets — 3 соб.: программа есть
A53: S052 | B53: Выставки и музеи | C53: University of Cambridge Museums (сводный) | D53: Агрегатор | E53: https://www.museums.cam.ac.uk/whats-on | F53: Все университетские музеи, включая семейные | G53: Центр | H53: HTML | I53: Еженедельно | J53: 1 | K53: да | L53: v0.4: сводная афиша 8 музеев (Drupal), фидов и JSON-LD нет — HTML Этап 6: подключён — сводная афиша 8 музеев (HTML, один запрос на весь список) + 4 запроса по фильтрам «для кого»/«тип» → категория family по разметке музеев | M53: https://www.museums.cam.ac.uk/whats-on | N53: разрешено | O53: 2026-09-28 | P53: события ведут к: продавец не определён — 13 соб.; DigiTickets — 8 соб.: программа есть; Eventbrite — 5 соб.: программа есть
A54: S053 | B54: Выставки и музеи | C54: IWM Duxford | D54: Площадка | F54: Авиашоу и события | G54: 30 мин | H54: HTML | I54: Еженедельно | J54: 2 | K54: нет | L54: Этап 5: закрыт — iwm.org.uk — 403 (бот-защита) на все страницы; в Ents24/Skiddle Duxford не найден | N54: — | O54: 2026-09-28
A55: S054 | B55: Детям и семьям | C55: Cambridge Science Centre | D55: Площадка | F55: Детские научные программы | G55: Центр | H55: HTML | I55: Еженедельно | J55: 2 | K55: да | L55: Этап 5: отложен — WordPress, тип записей events без дат в API — нужен разбор HTML (детские события — ценно) Этап 6: подключён — ссылки — из RSS /whats-on/feed/, дата и время — со страницы события; все события — семейные (family) | M55: https://www.cambridgesciencecentre.org/whats-on/feed/ | N55: разрешено | O55: 2026-09-28 | P55: события ведут к: своя касса (cambridgesciencecentre.org) — 4 соб.: программы нет
A56: S055 | B56: Детям и семьям | C56: Библиотеки Cambridgeshire | D56: Организатор | F56: Детские чтения, каникулярные программы | G56: Центр + 30 мин | H56: HTML | I56: Еженедельно | J56: 2 | K56: да | L56: Этап 5: отложен — Contensis, события библиотек — на сторонних сервисах; нужен разбор Этап 6: подключён — события библиотек — на Eventbrite (страница организатора со страницы совета), JSON-LD страниц событий; серии помечены «recurring series» | M56: https://www.cambridgeshire.gov.uk/residents/libraries-leisure-culture/libraries | N56: разрешено | O56: 2026-09-28 | P56: Eventbrite: есть — Eventbrite Affiliate Program (в условиях не указана (обзоры: impact.com))
A57: S056 | B57: Детям и семьям | C57: Семейные программы музеев | D57: Агрегатор | F57: См. University of Cambridge Museums | G57: Центр | H57: Производный (тег «дети») | I57: — | J57: 1 | K57: — | L57: Тегировать «дети» из музейных источников. v0.4: отдельного сайта нет: тегировать «дети» события из S050, S051, S052, S069 Этап 6: производный — тег «дети» из музейных источников — теперь по разметке S052/S048/S001 (категория family) и KIDS_RE | N57: — | O57: 2026-09-28
A58: S057 | B58: Еда и напитки | C58: Eat Cambridge | D58: Организатор | F58: Фуд-фестиваль и сопутствующие события | G58: Центр | H58: HTML | I58: Сезонно | J58: 2 | K58: да | L58: Этап 5: ежегодное — фестиваль в мае; фид — 3 записи | M58: https://eat-cambridge.co.uk/feed/ | N58: разрешено | O58: 2026-09-28
A59: S058 | B59: Еда и напитки | C59: Открытия ресторанов | D59: СМИ | F59: Через Cambridge Independent / Cambridge News | G59: Центр | H59: RSS СМИ | I59: Еженедельно | J59: 2 | K59: — | L59: Этап 5: не нужен — производный источник: открытия через S092/S093 (извлечение из статей) | N59: — | O59: 2026-09-28
A60: S059 | B60: Рынки и барахолки | C60: Cambridge Market (Market Square) | D60: Площадка | E60: https://www.cambridge.gov.uk | F60: Ежедневный рынок, воскресный фермерский | G60: Центр | H60: Ручной (стабильное расписание) | I60: Ежемесячно | J60: 3 | K60: — | L60: Этап 6: не нужен — Cambridge Market — ежедневный рынок, стабильное расписание: справочник, не событие | O60: 2026-09-28
A61: S060 | B61: Рынки и барахолки | C61: All Saints Garden Art & Craft Market | D61: Площадка | F61: Рынок местных мастеров | G61: Центр | H61: Ручной | I61: Ежемесячно | J61: 3 | K61: — | L61: Этап 6: не нужен — All Saints Garden Art & Craft Market — регулярный (суббота), справочник | O61: 2026-09-28
A62: S061 | B62: Рынки и барахолки | C62: Car boot sales в округе | D62: Агрегатор | F62: Воскресные барахолки | G62: 30 мин | H62: HTML агрегатора (найти) | I62: Еженедельно | J62: 3 | K62: — | L62: Этап 6: не нужен — car boot sales — агрегатора с разрешающим robots.txt не нашлось; регулярные — справочник | O62: 2026-09-28
A63: S062 | B63: Комедия и стендап | C63: Комедия на Corn Exchange / Junction / ADC | D63: Площадка | F63: См. площадки | G63: Центр | H63: Производный (тег «комедия») | I63: — | J63: 1 | K63: — | L63: Тегировать «комедия» из этих источников. v0.4: отдельного сайта нет: тегировать «комедия» события из S011, S012, S042 (+ Ents24 ComedyEvent) Этап 6: производный — тег «комедия» из S011, S012, S042 | N63: — | O63: 2026-09-28
A64: S063 | B64: Ночная жизнь | C64: Resident Advisor / Skiddle — клубные события | D64: Агрегатор | F64: Клубные вечера | G64: Центр | H64: HTML / API Skiddle | I64: Еженедельно | J64: 3 | K64: нет | L64: Этап 6: покрыт — Resident Advisor — 403; клубные события — Skiddle (S007, S129) | O64: 2026-09-28
A65: S064 | B65: Ночная жизнь | C65: Квизы в пабах | D65: — | F65: Регулярные квизы | G65: Центр | H65: Ручной (стабильные) | I65: Ежемесячно | J65: 3 | K65: — | L65: Скорее справочник, чем лента Этап 6: не нужен — квизы в пабах — справочник, не лента событий | O65: 2026-09-28
A66: S065 | B66: Открытые двери и экскурсии | C66: Open Cambridge | D66: Организатор | E66: https://www.opencambridge.cam.ac.uk/ | F66: Открытые двери, сентябрь | G66: Центр | H66: HTML (curl, пауза 10 с) | I66: Ежегодно | J66: 1 | K66: да | L66: Часть Heritage Open Days. v0.4: решение после этапа 1: curl с честным User-Agent и паузой 10 с; ежегодно (сентябрь), часть Heritage Open Days Этап 6: ежегодное — через recurring_events (R12) | M66: https://www.opencambridge.cam.ac.uk/ | N66: разрешено, Crawl-delay 10 | O66: 2026-09-28
A67: S066 | B67: Открытые двери и экскурсии | C67: Heritage Open Days | D67: Агрегатор | F67: Национальная программа открытых дверей | G67: Центр + час | H67: HTML (поиск по региону) | I67: Сезонно | J67: 2 | K67: да | L67: Этап 5: ежегодное — Heritage Open Days — сентябрь; поиск по региону в HTML | M67: https://www.heritageopendays.org.uk | N67: разрешено | O67: 2026-09-28
A68: S067 | B68: Открытые двери и экскурсии | C68: National Garden Scheme | D68: Агрегатор | E68: https://findagarden.ngs.org.uk | F68: Частные сады, открытые для посещения | G68: 30 мин + час | H68: JSON (API приложения) | I68: Ежедневно | J68: 2 | K68: да | L68: Этап 5: отложен — findagarden.ngs.org.uk — сезон весна–лето; разбор HTML Этап 6: отложен — NGS (открытые сады): приложение findagarden на скриптах; сезон апрель–сентябрь — проверить API весной Этап 7b: подключён — открытый API приложения findagarden (robots.txt разрешает): сады Кембриджшира и в 75 км, открытия с датой и ценой; подряд идущие дни — одним событием (Robinson College — ежедневно до 22 декабря). | M68: https://api.findagarden.ngs.org.uk/api/gardens | N68: разрешено | O68: 2026-09-30
A69: S068 | B69: Открытые двери и экскурсии | C69: Колледжи — дни открытых дверей и туры | D69: Организатор | F69: Посещения колледжей | G69: Центр | H69: Ручной | I69: Сезонно | J69: 3 | K69: — | L69: Этап 6: вручную — дни открытых дверей колледжей — Open Cambridge (R12) и University What's On (S048) | O69: 2026-09-28
A70: S069 | B70: Природа и загородные поездки | C70: Cambridge University Botanic Garden | D70: Площадка | E70: https://www.botanic.cam.ac.uk | F70: События, сезонные экскурсии | G70: Центр | H70: HTML | I70: Еженедельно | J70: 1 | K70: да | L70: v0.4: WordPress, фида событий нет; REST закрыт (401) Этап 6: подключён — HTML /whats-on/ + страницы событий; часть событий есть и в S052 | M70: https://www.botanic.cam.ac.uk/whats-on/ | N70: разрешено | O70: 2026-09-28 | P70: события ведут к: Ticket Tailor — 2 соб.: программы нет; своя касса (botanic.cam.ac.uk) — 1 соб.: программы нет
A71: S070 | B71: Природа и загородные поездки | C71: National Trust: Wimpole, Anglesey Abbey, Wicken Fen | D71: Площадка | E71: https://www.nationaltrust.org.uk/visit/cambridgeshire/wimpole-estate/events | F71: Сезонные события, фестивали огней, детские программы | G71: 30 мин | H71: Ручной сезонный | I71: Еженедельно | J71: 1 | K71: нет | L71: v0.4: решение после этапа 1: защиту Radware не обходим; вносить вручную по сезонам (Wimpole, Anglesey Abbey, Wicken Fen) Этап 6: вручную — National Trust — защита Radware; ручной сезонный календарь | M71: https://www.nationaltrust.org.uk/visit/cambridgeshire/wimpole-estate/events | N71: разрешено | O71: 2026-09-28 | P71: National Trust: есть — но на членство, магазин и отдых (Awin: Memberships 3795, Shop 3974, Holidays 12045); билеты на события — не указаны (Awin)
A72: S071 | B72: Природа и загородные поездки | C72: Ely Cathedral | D72: Площадка | F72: Концерты, рынки, сезонные события | G72: 30 мин | H72: HTML | I72: Еженедельно | J72: 2 | K72: да | L72: Этап 5: отложен — Spektrix без JSON-LD; часть концертов уже из Ents24/Skiddle (S128/S129) и Eventbrite Этап 6: подключён — Ely Cathedral: карточки /events (дата + название), один запрос; отложен в P2 на этапе 5 | M72: https://www.elycathedral.org | N72: разрешено | O72: 2026-09-28 | P72: события ведут к: Spektrix (касса площадки) — 3 соб.: программы нет; Eventbrite — 1 соб.: программа есть
A73: S072 | B73: Праздники и сезонное | C73: Cambridge City Council — городские события | D73: Организатор | E73: https://www.camcityevents.co.uk/events | F73: Фейерверки на Midsummer Common, рождественские огни, Midsummer Fair | G73: Центр | H73: HTML | I73: Еженедельно | J73: 1 | K73: да | L73: Фейерверки собирают до 20 тыс. человек — обязательно в выпуск. v0.4: городские события (фейерверки, Kidmas Lights) — на camcityevents.co.uk (та же платформа, что у Corn Exchange); cambridge.gov.uk/fireworks туда редиректит | M73: https://www.camcityevents.co.uk/events | N73: разрешено | O73: 2026-09-27 | P73: события ведут к: Cambridge Live (касса Corn Exchange и Guildhall) — 1 соб.: программы нет; своя касса (camcityevents.co.uk) — 1 соб.: программы нет
A74: S073 | B74: Праздники и сезонное | C74: Remembrance, Pancake Race и др. традиции | D74: Организатор | F74: Сезонные традиции | G74: Центр | H74: Ручной календарь | I74: Ежегодно | J74: 3 | K74: — | L74: Завести статичный годовой календарь Этап 6: вручную — традиции (Remembrance, Pancake Race) — статичный календарь / recurring вручную; Remembrance в Эли — пришло из статьи Ely Standard | O74: 2026-09-28
A75: S074 | B75: Воркшопы и курсы | C75: Makespace Cambridge | D75: Организатор | F75: Мастерская: воркшопы, дни открытых дверей | G75: Центр | H75: HTML | I75: Еженедельно | J75: 3 | K75: нет | L75: Этап 6: закрыт — Makespace: 429 на robots.txt — считаем запретом; курсы для членов, не публичные события | O75: 2026-09-28
A76: S075 | B76: Воркшопы и курсы | C76: Воркшопы в музеях | D76: Агрегатор | F76: См. музеи | G76: Центр | H76: — | I76: — | J76: 2 | K76: — | L76: Этап 5: не нужен — производный (музеи) | N76: — | O76: 2026-09-28
A77: S076 | B77: Сообщества и благотворительность | C77: Love Mill Road / Mill Road Fringe | D77: Организатор | E77: https://www.millroadwinterfair.org/mill-road-fringe/ | F77: Районные события Mill Road в течение года | G77: Центр | H77: HTML | I77: Еженедельно | J77: 2 | K77: да | L77: Этап 5: отложен — Mill Road Fringe — сезонно; страница WordPress без событийных данных Этап 6: отложен — Mill Road Fringe: страница без дат, фестиваль летом — проверить к сезону; Winter Fair — в recurring (R16) | M77: https://www.millroadwinterfair.org/feed/ | N77: разрешено | O77: 2026-09-28
A78: S077 | B78: Сообщества и благотворительность | C78: Районные FB-группы и Nextdoor | D78: Соцсети | F78: Районные события, отмены | G78: Центр | H78: Ручной мониторинг (не парсить — правила платформ) | I78: Еженедельно | J78: 2 | K78: — | L78: Этап 5: не нужен — соцсети — по правилам не парсим | N78: — | O78: 2026-09-28
A79: S078 | B79: Практическое | C79: Перекрытия дорог (county council / one.network) | D79: Госорган | F79: Дорожные работы и перекрытия под события | G79: Центр + 30 мин | H79: HTML / фид (проверить) | I79: Ежедневно | J79: 2 | K79: нет | L79: Этап 5: закрыт — robots.txt запрещает | N79: запрещено | O79: 2026-09-28
A80: S079 | B80: Практическое | C80: Greater Anglia / Thameslink / National Rail | D80: Транспорт | F80: Инженерные работы, забастовки | G80: Центр + час | H80: HTML / API National Rail (проверить) | I80: Ежедневно | J80: 2 | K80: да | L80: Этап 5: не нужен — не события (транспорт); вернуться к этому, если понадобится практический блок | M80: https://www.nationalrail.co.uk | N80: разрешено | O80: 2026-09-28
A81: S080 | B81: Практическое | C81: Stagecoach East / Park & Ride | D81: Транспорт | F81: Изменения автобусов в дни событий | G81: Центр | H81: HTML | I81: Еженедельно | J81: 3 | K81: — | L81: Этап 6: не нужен — Stagecoach / Park & Ride — транспорт, не события (рубрики «Практическое» в выпуске нет) | O81: 2026-09-28
A82: S081 | B82: Фестивали | C82: Thriplow Daffodil Weekend | D82: Организатор | E82: https://www.thriplowdaffodils.org.uk | F82: Нарциссовый фестиваль в деревне Thriplow, март; до 10 тыс. гостей, деревня без машин | G82: 30 мин | H82: HTML | I82: Ежегодно | J82: 1 | K82: да | L82: Бывали отмены, если нарциссы не зацвели — мониторить Этап 6: ежегодное — через recurring_events (R02) | M82: https://www.thriplowdaffodils.org.uk | N82: разрешено | O82: 2026-09-28
A83: S082 | B83: Спорт — смотреть | C83: Cambridge Dragon Boat Festival (ACT) | D83: Организатор | E83: https://act4addenbrookes.org.uk | F83: Гонки драконьих лодок на Cam у Fen Ditton, сентябрь; 48 корпоративных команд, семейная программа на берегу | G83: Центр | H83: HTML | I83: Ежегодно | J83: 1 | K83: да | L83: Благотворительный, в пользу Addenbrooke's. v0.4: ежегодно; /feed/ — новости; в WP REST есть тип events — проверить на этапе 2 Этап 6: ежегодное — через recurring_events (R10) | M83: https://act4addenbrookes.org.uk/dragonboat/ | N83: разрешено | O83: 2026-09-28
A84: S083 | B84: Фестивали | C84: «Nihao! China» Cambridge Dragon Boat Festival | D84: Организатор | F84: Китайский фестиваль драконьих лодок на Jesus Green и Cam, июнь | G84: Центр | H84: Ручной (ежегодно) | I84: Ежегодно | J84: 2 | K84: да | L84: Этап 5: ежегодное — фестиваль в июне; билеты на Eventbrite (S008) | M84: https://www.eventbrite.com/e/nihao-china-cambridge-dragon-boat-festival-2026-tickets-1985873566295 | N84: разрешено | O84: 2026-09-28 | P84: Eventbrite: есть — Eventbrite Affiliate Program (в условиях не указана (обзоры: impact.com))
A85: S084 | B85: Спорт — смотреть | C85: Cambridgeshire Cats (американский футбол) | D85: Клуб | F85: BAFA Premier Division South, домашние игры в Shelford Rugby Club | G85: 30 мин | H85: HTML / соцсети | I85: Еженедельно в сезон | J85: 2 | K85: да | L85: Этап 5: отложен — сайт WordPress (новости), страницы расписания нет; сезон BAFA — весна–лето, сейчас матчей нет Этап 6c: не сезон — Cambridgeshire Cats (американский футбол): сезон BAFA весна–лето, в октябре игр нет — подключить к началу сезона | M85: https://cambridgeshirecats.com/feed/ | N85: разрешено | O85: 2026-09-29
A86: S085 | B86: Спорт — смотреть | C86: Cambridge Pythons (университетский ам. футбол) | D86: Клуб | F86: BUAFL, университетская лига | G86: Центр | H86: HTML / соцсети | I86: Еженедельно в сезон | J86: 3 | K86: нет | L86: Этап 6: отложен — Cambridge Pythons: сайт отвечает 502, сезон BAFA весна–лето — проверить весной вместе с Cambridgeshire Cats (R18) | O86: 2026-09-28
A87: S086 | B87: Сообщества и благотворительность | C87: Addenbrooke's Charitable Trust — события | D87: Организатор | E87: https://act4addenbrookes.org.uk | F87: Благотворительные забеги, лодки, челленджи | G87: Центр + 30 мин | H87: HTML | I87: Еженедельно | J87: 2 | K87: да | L87: Этап 5: отложен — WordPress events + RSS; благотворительные забеги и челленджи — разбор HTML Этап 6: не нужен — Addenbrooke's Charitable Trust: благотворительные забеги и акции для участников, не события для зрителей; Dragon Boat Festival — в recurring (R10) | M87: https://act4addenbrookes.org.uk/feed/ | N87: разрешено | O87: 2026-09-28
A88: S087 | B88: Еда и напитки | C88: The Cambridge Foodies | D88: Блог / СМИ | E88: https://cambridgefoodies.me.uk | F88: Открытия и обзоры ресторанов и кафе, в т.ч. Mill Road, Ely, Royston | G88: Центр + 30 мин | H88: RSS | I88: Ежедневно | J88: 1 | K88: да | L88: Поймал Catte Latte, Hungarian Soul, Buren, Urban Larder. Часть постов рекламные (помечены «ad»), часть за платной подпиской. v0.4: поток «новое в городе», не афиша | M88: https://cambridgefoodies.me.uk/feed/ | N88: разрешено | O88: 2026-09-27
A89: S088 | B89: Спорт — участвовать | C89: parkrun — Cambridge, Wimpole и др. | D89: Организатор | E89: https://www.parkrun.org.uk | F89: Еженедельные бесплатные 5 км по субботам 9:00, junior parkrun по воскресеньям | G89: Центр + 30 мин | H89: Статичный справочник + ручной (спецзабеги: Рождество, Новый год, отмены) | I89: Еженедельно | J89: 2 | K89: нет | L89: Этап 5: закрыт — parkrun.org.uk: robots.txt отвечает 403 — считаем запретом; регулярные забеги — статичный справочник вручную | N89: — | O89: 2026-09-28
A90: S089 | B90: Спорт — участвовать | C90: Town and Gown 10k | D90: Организатор | E90: https://www.townandgown10k.com/ | F90: 10 км, октябрь, старт на Midsummer Common, ~3000 участников | G90: Центр | H90: Через Cambridge News (S004) и Cambridge 105 (S005) | I90: Ежегодно | J90: 1 | K90: нет | L90: Нужен и для рубрики «Практическое» — перекрытия. v0.4: решение после этапа 1: защиту не обходим; ловим по новостям Cambridge News и Cambridge 105, официальный сайт townandgown10k.com (MDUK) Этап 6: ежегодное — Cloudflare; через статьи и recurring_events (R14, вручную) | N90: robots.txt: 403 | O90: 2026-09-28
A91: S090 | B91: Ночная жизнь | C91: DesignMyNight — Cambridge | D91: Агрегатор / бронирование | E91: https://www.designmynight.com/cambridge | F91: Бары, рестораны, мероприятия в заведениях | G91: Центр | H91: — (robots.txt запрещает) | I91: Еженедельно | J91: 1 | K91: нет | L91: Добавлен в v0.4 (решение после этапа 1). v0.4: не собираем; возможен только как справочник заведений для «новое в городе» Этап 6: не собираем — robots.txt запрещает раздел событий | M91: https://www.designmynight.com/cambridge | N91: запрещено: /cambridge/whats-on, /api/ | O91: 2026-09-28
A92: S091 | B92: Сквозные агрегаторы | C92: Cambridge Live Tickets | D92: Билетная система | E92: https://www.cambridgelivetickets.co.uk | F92: Corn Exchange, Guildhall, городские события Cambridge Live | G92: Центр | H92: HTML + JSON-LD | I92: Ежедневно | J92: 1 | K92: да | L92: Добавлен в v0.4 (решение после этапа 1). v0.4: список ?page=1..4 в HTML (~24 на страницу), JSON-LD Event с postcode на странице события; пересекается с S011 и S072 | M92: https://www.cambridgelivetickets.co.uk/events | N92: разрешено | O92: 2026-09-27 | P92: события ведут к: Cambridge Live (касса Corn Exchange и Guildhall) — 11 соб.: программы нет
A93: S092 | B93: Новое в городе | C93: Cambridge Independent — News/Business | D93: СМИ (RSS) | E93: https://www.cambridgeindependent.co.uk/rss-feeds/ | F93: Открытия/закрытия заведений, отмены | G93: Центр + час | H93: RSS + извлечение Claude | I93: Ежедневно | J93: 1 | K93: да | L93: Добавлен в v0.4 (бриф v3, «Новое в городе»). v0.4: по 20 записей в Business и News; коллектор collectors/sources/cambridge_independent_business.py | M93: https://www.cambridgeindependent.co.uk/_api/rss/cambridge_independent_business_feed.xml (+ news_feed.xml) | N93: разрешено | O93: 2026-09-27 | P93: события ведут к: продавец не определён — 3 соб.
A94: S093 | B94: Новое в городе | C94: Cambridge News — Food & Drink, Shopping | D94: СМИ (RSS) | E94: https://www.cambridge-news.co.uk/all-about/food-and-drink | F94: Открытия ресторанов, кафе, магазинов | G94: Центр + час | H94: RSS + извлечение Claude | I94: Ежедневно | J94: 1 | K94: да | L94: Добавлен в v0.4 (бриф v3, «Новое в городе»). v0.4: раздела /news/business/ нет (404); есть теги all-about/food-and-drink и all-about/shopping с RSS (?service=rss); общий фид новостей — в S004 | M94: https://www.cambridge-news.co.uk/all-about/food-and-drink?service=rss (+ shopping) | N94: разрешено | O94: 2026-09-27
A95: S094 | B95: Новое в городе | C95: Grand Arcade — магазины | D95: Торговый центр | E95: https://www.grandarcade.co.uk/ | F95: Новые арендаторы | G95: Центр | H95: HTML (список магазинов, сравнение) | I95: Еженедельно | J95: 1 | K95: да | L95: Добавлен в v0.4 (бриф v3, «Новое в городе»). v0.4: RSS пуст, раздела новостей нет; 55 магазинов в /stores/ — новые арендаторы по сравнению с прошлым прогоном (первый прогон — база) | M95: https://www.grandarcade.co.uk/stores/ | N95: разрешено | O95: 2026-09-27
A96: S095 | B96: Новое в городе | C96: Lion Yard — магазины | D96: Торговый центр | E96: https://www.thelionyard.co.uk/ | F96: Новые арендаторы | G96: Центр | H96: HTML (список магазинов, сравнение) | I96: Еженедельно | J96: 1 | K96: да | L96: Добавлен в v0.4 (бриф v3, «Новое в городе»). v0.4: официальный сайт — thelionyard.co.uk (lionyard.co.uk не отвечает); новостей нет; data-name у каждого магазина | M96: https://www.thelionyard.co.uk/stores/ | N96: разрешено | O96: 2026-09-27
A97: S096 | B97: Новое в городе | C97: The Grafton — магазины | D97: Торговый центр | E97: https://graftoncentre.co.uk/ | F97: Новые арендаторы | G97: Центр | H97: HTML (список магазинов, сравнение) | I97: Еженедельно | J97: 1 | K97: да | L97: Добавлен в v0.4 (бриф v3, «Новое в городе»). v0.4: RSS /feed/ пуст; список /stores/ | M97: https://graftoncentre.co.uk/stores/ | N97: разрешено | O97: 2026-09-27
A98: S097 | B98: Новое в городе | C98: Cambridge BID — новости | D98: Организация (RSS) | E98: https://www.cambridgebid.co.uk/news | F98: Новости центра города, городские события | G98: Центр | H98: RSS (без Claude до решения) | I98: Еженедельно | J98: 1 | K98: да | L98: Добавлен в v0.4 (бриф v3, «Новое в городе»). v0.4: Squarespace; robots.txt закрывает сайт для ИИ-краулеров (anthropic-ai, GPTBot и др.) — наш User-Agent не в списке, но статьи в Claude не передаём до решения владельца | M98: https://www.cambridgebid.co.uk/news?format=rss | N98: разрешено | O98: 2026-09-27
A99: S098 | B99: Расширение географии (этап 5) | C99: South Cambridgeshire District Council | D99: Совет | E99: https://www.scambs.gov.uk | F99: Район South Cambridgeshire | G99: Час / Кембриджшир | H99: HTML | I99: Ежедневно | J99: 2 | K99: да | L99: Этап 5: отложен — страница /events есть, событийных данных нет Этап 6: не нужен — South Cambridgeshire DC: календарь — заседания совета, не публичные события | M99: https://www.scambs.gov.uk | N99: разрешено | O99: 2026-09-28
A100: S099 | B100: Расширение географии (этап 5) | C100: East Cambridgeshire District Council | D100: Совет | E100: https://www.eastcambs.gov.uk | F100: Район East Cambridgeshire (Ely, Soham) | G100: Час / Кембриджшир | H100: HTML | I100: Ежедневно | J100: 2 | K100: да | L100: Этап 5: отложен — Drupal, /events без структурированных данных Этап 6: не нужен — East Cambridgeshire DC: страница событий пуста | M100: https://eastcambs.gov.uk/ | N100: разрешено | O100: 2026-09-28
...

Sheet Проверка P1
A1: ID | B1: Источник | C1: URL проверен | D1: Способ сбора | E1: Endpoint | F1: Что нашёл | G1: Что не получилось
A2: S001 | B2: Visit Cambridge — events | C2: да | D2: API + HTML | E2: https://www.visitcambridge.org/wp-json/vc-map/v1/events | F2: https://www.visitcambridge.org — 200; alternate-фиды: https://www.visitcambridge.org/wp-json/wp/v2/pages/26, https://www.visitcambridge.org/wp-json/oembed/1.0/embed?url=https%3A%2F%2Fwww.visitcambridge.org%2F; WordPress https://www.visitcambridge.org/whats-on/ — 200; alternate-фиды: https://www.visitcambridge.org/wp-json/wp/v2/pages/553, https://www.visitcambridge.org/wp-json/oembed/1.0/embed?url=https%3A%2F%2Fwww.visitcambridge.org%2Fwhats-on%2F; WordPress https://www.visitcambridge.org/event-categories/festivals/ — 200; alternate-фиды: https://www.visitcambridge.org/event-categories/festivals/feed/; WordPress https://www.visitcambridge.org/wp-json/vc-map/v1/events — 200; JSON
A3: S002 | B3: What's On In Cambridge | C3: да | D3: RSS | E3: https://www.whatsonincambridge.com/feed/ | F3: https://www.whatsonincambridge.com/__superjs/challenge?u=%2Fevents%2F — 200 https://www.whatsonincambridge.com/feed/ — 200; фид, записей: 10 | G3: https://www.whatsonincambridge.com/events/ — JS-проверка «SuperJS» (бот-блок), HTML без браузера недоступен
A4: S003 | B4: Cambridge Independent — What's On | C4: да | D4: RSS | E4: https://www.cambridgeindependent.co.uk/_api/rss/cambridge_independent_whatson_feed.xml | F4: https://www.cambridgeindependent.co.uk/whats-on/ — 200 https://www.cambridgeindependent.co.uk/_api/rss/cambridge_independent_whatson_feed.xml — 200; фид, записей: 20
A5: S004 | B5: Cambridge News / CambridgeshireLive | C5: да | D5: RSS | E5: https://www.cambridge-news.co.uk/whats-on/?service=rss | F5: https://www.cambridge-news.co.uk — 200; alternate-фиды: https://www.cambridge-news.co.uk/rss.xml https://www.cambridge-news.co.uk/whats-on/ — 200; alternate-фиды: https://www.cambridge-news.co.uk/whats-on/rss.xml; билетная система: ecal https://www.cambridge-news.co.uk/?service=rss — 200; фид, записей: 25 https://www.cambridge-news.co.uk/whats-on/?service=rss — 200; фид, записей: 15 https://www.cambridge-news.co.uk/whats-on/?service=rss — 200; фид, записей: 15
A6: S005 | B6: Cambridge 105 — события | C6: да | D6: iCal | E6: https://cambridge105.co.uk/whatson/?ical=1 | F6: https://cambridge105.co.uk — 200; alternate-фиды: https://cambridge105.co.uk/whatson/?ical=1, https://cambridge105.co.uk/wp-json/wp/v2/pages/44141, https://cambridge105.co.uk/wp-json/oembed/1.0/embed?url=https%3A%2F%2Fcambridge105.co.uk%2F; WordPress https://cambridge105.co.uk/events/ — 200; alternate-фиды: https://cambridge105.co.uk/whatson/?ical=1, https://cambridge105.co.uk/wp-json/wp/v2/media/75261, https://cambridge105.co.uk/wp-json/oembed/1.0/embed?url=https%3A%2F%2Fcambridge105.co.uk%2Fevents%2F; WordPress https://cambridge105.co.uk/feed/ — 200; фид, записей: 30 https://cambridge105.co.uk/events/?ical=1 — 200; iCal, событий: 22 https://cambridge105.co.uk/wp-json/tribe/events/v1/events — 200; JSON https://cambridge105.co.uk/whatson/?ical=1 — 200; iCal, событий: 22
A7: S006 | B7: Ents24 — Cambridge | C7: да | D7: JSON-LD | E7: https://www.ents24.com/whatson/cambridge | F7: https://www.ents24.com/whatson/cambridge — 200; JSON-LD Event: 37; билетная система: ents24, gigantic
A8: S007 | B8: Skiddle — Cambridge | C8: да | D8: JSON-LD | E8: https://www.skiddle.com/whats-on/Cambridge/ | F8: https://www.skiddle.com/whats-on/Cambridge/ — 200; JSON-LD Event: 49; билетная система: ecal, skiddle https://www.skiddle.com/api/ — 200; билетная система: skiddle
A9: S008 | B9: Eventbrite — Cambridge | C9: да | D9: JSON-LD | E9: https://www.eventbrite.co.uk/d/united-kingdom--cambridge/all-events/?page=N | F9: https://www.eventbrite.co.uk — 200; билетная система: eventbrite https://www.eventbrite.co.uk/d/united-kingdom--cambridge/all-events/ — 200; JSON-LD Event: 20; билетная система: eventbrite
A10: S011 | B10: Cambridge Corn Exchange | C10: да | D10: HTML + JSON-LD | E10: https://www.cornex.co.uk/events | F10: https://www.cambridgelivetickets.co.uk/ — 200 https://www.cornex.co.uk — 200 https://www.cornex.co.uk/events — 200 https://www.cambridgelivetickets.co.uk — 200 https://www.cornex.co.uk/events/alison-moyet-2 — 200; JSON-LD Event: 1
A11: S012 | B11: Cambridge Junction | C11: да | D11: API + HTML | E11: https://www.junction.co.uk/wp-json/wp/v2/cj_events | F11: https://www.junction.co.uk — 200; alternate-фиды: https://www.junction.co.uk/feed/, https://www.junction.co.uk/comments/feed/, https://www.junction.co.uk/wp-json/oembed/1.0/embed?url=https%3A%2F%2Fwww.junction.co.uk%2F; WordPress; билетная система: ecal, spektrix https://www.junction.co.uk/whats-on/ — 200; alternate-фиды: https://www.junction.co.uk/feed/, https://www.junction.co.uk/comments/feed/, https://www.junction.co.uk/wp-json/oembed/1.0/embed?url=https%3A%2F%2Fwww.junction.co.uk%2Fwhats-on%2F; WordPress; билетная система: ecal, spektrix https://www.junction.co.uk/wp-json/wp/v2/cj_events?per_page=20 — 200; JSON https://www.junction.co.uk/feed/ — 200; фид, записей: 12
A12: S018 | B12: Cambridge United | C12: да | D12: iCal (fixtur.es) + HTML | E12: https://ics.fixtur.es/v2/home/cambridge-united-fc.ics | F12: https://www.cambridgeunited.com — 200 https://fixtur.es/en/team/cambridge-united-fc/home — 200; JSON-LD Event: 27 https://www.cambridgeunited.com/fixture/list/57 — 200 https://ics.fixtur.es/v2/home/cambridge-united-fc.ics — 200; iCal, событий: 188
A13: S021 | B13: Newmarket Racecourses | C13: да | D13: JSON-LD | E13: https://www.thejockeyclub.co.uk/newmarket/events-tickets/ | F13: https://www.thejockeyclub.co.uk/newmarket/ — 200 https://www.thejockeyclub.co.uk/newmarket/events-tickets/ — 200; JSON-LD Event: 14
A14: S026 | B14: Chariots of Fire | C14: да | D14: JSON-LD (RunThrough) | E14: https://www.runthrough.co.uk/event/chariots-of-fire-september-2026 | F14: https://www.chariots-of-fire.co.uk/ — 200; alternate-фиды: https://www.chariots-of-fire.co.uk/feed/, https://www.chariots-of-fire.co.uk/comments/feed/, https://www.chariots-of-fire.co.uk/wp-json/wp/v2/pages/21; WordPress https://www.chariots-of-fire.co.uk/feed/ — 200; фид, записей: 10 https://www.runthrough.co.uk/event/chariots-of-fire-september-2026 — 200; JSON-LD Event: 1
A15: S028 | B15: Cambridge Half Marathon | C15: да | D15: HTML | E15: https://cambridgehalfmarathon.com/ | F15: https://cambridgehalfmarathon.com/ — 200
A16: S030 | B16: Cambridge Festival (университет) | C16: да | D16: HTML (curl, пауза 10 с) | E16: https://www.festival.cam.ac.uk/events | F16: https://www.festival.cam.ac.uk/events — 200 через curl, robots.txt разрешает (Crawl-delay: 10); фидов и JSON-LD нет | G16: Pantheon отдаёт 403 Python-клиенту httpx (и на robots.txt), curl с тем же User-Agent — 200: блок по отпечатку клиента
A17: S031 | B17: Cambridge Folk Festival | C17: да | D17: HTML | E17: https://www.cambridgefolkfestival.co.uk/ | F17: https://www.cambridgefolkfestival.co.uk/ — 200 https://www.cambridgefolkfestival.co.uk/ — 200
A18: S032 | B18: Cambridge Beer Festival | C18: да | D18: iCal | E18: https://www.cambridgebeerfestival.com/events/?ical=1 | F18: https://www.cambridgebeerfestival.com — 200; JSON-LD Event: 2; alternate-фиды: https://www.cambridgebeerfestival.com/events/?ical=1; WordPress + The Events Calendar; билетная система: ecal
A19: S033 | B19: Strawberry Fair | C19: да | D19: JSON-LD | E19: https://strawberry-fair.org.uk/ | F19: https://strawberry-fair.org.uk/ — 200; JSON-LD Event: 1 https://strawberry-fair.org.uk/feed/ — 200; JSON-LD Event: 1
A20: S038 | B20: Mill Road Winter Fair | C20: да | D20: RSS | E20: https://www.millroadwinterfair.org/feed/ | F20: https://www.millroadwinterfair.org — 200; alternate-фиды: https://www.millroadwinterfair.org/feed/, https://www.millroadwinterfair.org/comments/feed/, https://www.millroadwinterfair.org/wp-json/wp/v2/pages/22; WordPress https://www.millroadwinterfair.org/feed/ — 200; фид, записей: 0
A21: S039 | B21: Рождественские маркеты в центре | C21: да | D21: HTML | E21: https://www.christmasincambridge.co.uk/ | F21: https://www.christmasincambridge.co.uk/ — 200 https://www.visitcambridge.org/event/christmas-in-cambridge/ — 200; alternate-фиды: https://www.visitcambridge.org/wp-json/oembed/1.0/embed?url=https%3A%2F%2Fwww.visitcambridge.org%2Fevent%2Fchristmas-in-cambridge%2F; WordPress
A22: S041 | B22: Cambridge Arts Theatre | C22: проверить | D22: Через Ents24 (S006) | G22: https://www.artstheatre.co.uk — 403, Cloudflare challenge (cf-mitigated) и для httpx, и для curl
A23: S042 | B23: ADC Theatre | C23: да | D23: iCal | E23: https://www.camdram.net/venues/adc-theatre/diary.ics | F23: https://www.adctheatre.com — 200; билетная система: spektrix https://www.adctheatre.com/whats-on/ — 200; билетная система: spektrix https://www.camdram.net/venues/adc-theatre/diary.ics — 200; iCal, событий: 28 https://www.camdram.net/venues/adc-theatre/diary.json — 200; JSON
A24: S045 | B24: Arts Picturehouse | C24: да | D24: HTML | E24: https://www.picturehouses.com/cinema/arts-picturehouse-cambridge | F24: https://www.picturehouses.com/cinema/arts-picturehouse-cambridge — 200; билетная система: ecal
A25: S047 | B25: Talks.cam | C25: да | D25: iCal | E25: https://talks.cam.ac.uk/show/ics/{5606,5462,5358,5769,23088}/ | F25: https://talks.cam.ac.uk — 200 https://talks.cam.ac.uk/document/documentation/ — 200 https://talks.cam.ac.uk/show/ics/5606/ — 200; iCal, событий: 15 https://talks.cam.ac.uk/show/ics/5462/ — 200; iCal, событий: 8 https://talks.cam.ac.uk/show/ics/5358/ — 200; iCal, событий: 8 https://talks.cam.ac.uk/show/ics/5769/ — 200; iCal, событий: 7 https://talks.cam.ac.uk/show/ics/23088/ — 200; iCal, событий: 55
A26: S048 | B26: University of Cambridge — What's On | C26: да | D26: HTML | E26: https://www.admin.cam.ac.uk/whatson/ | F26: https://www.admin.cam.ac.uk/whatson/ — 200 | G26: webservices.admin.cam.ac.uk (iCal 76 событий, RSS) — robots.txt: Disallow: / — не собираем без решения https://www.cam.ac.uk/whats-on — Pantheon 403 для httpx
A27: S050 | B27: Fitzwilliam Museum | C27: да | D27: RSS (выставки) + HTML (события) | E27: https://fitzmuseum.cam.ac.uk/feeds/exhibitions | F27: https://fitzmuseum.cam.ac.uk — 200; alternate-фиды: https://fitzmuseum.cam.ac.uk/feeds/news, https://fitzmuseum.cam.ac.uk/feeds/vacancies, https://fitzmuseum.cam.ac.uk/feeds/exhibitions https://fitzmuseum.cam.ac.uk/events — 200; alternate-фиды: https://fitzmuseum.cam.ac.uk/feeds/news, https://fitzmuseum.cam.ac.uk/feeds/vacancies, https://fitzmuseum.cam.ac.uk/feeds/exhibitions https://fitzmuseum.cam.ac.uk/feeds/exhibitions — 200; фид, записей: 20
A28: S051 | B28: Kettle's Yard | C28: да | D28: HTML | E28: https://www.kettlesyard.cam.ac.uk/whats-on/ | F28: https://www.kettlesyard.cam.ac.uk — 200 https://www.kettlesyard.cam.ac.uk/whats-on/ — 200 | G28: https://www.kettlesyard.cam.ac.uk/feed/ — 500 https://www.kettlesyard.co.uk — ConnectError: [SSL: CERTIFICATE_VERIFY_FAILED] certificate verify failed: Hostname mismatch, certificate is not valid for 'www.kettlesyard.co.uk'. (_ssl.c:1016) https://www.kettlesyard.co.uk/events/ — ConnectError: [SSL: CERTIFICATE_VERIFY_FAILED] certificate verify failed: Hostname mismatch, certificate is not valid for 'www.kettlesyard.co.uk'. (_ssl.c:1016) https://www.kettlesyard.co.uk/feed/ — ConnectError: [SSL: CERTIFICATE_VERIFY_FAILED] certificate verify failed: Hostname mismatch, certificate is not valid for 'www.kettlesyard.co.uk'. (_ssl.c:1016)
A29: S052 | B29: University of Cambridge Museums (сводный) | C29: да | D29: HTML | E29: https://www.museums.cam.ac.uk/whats-on | F29: https://www.museums.cam.ac.uk — 200 https://www.museums.cam.ac.uk/whats-on — 200
A30: S056 | B30: Семейные программы музеев | C30: проверить | D30: Производный (тег «дети») | G30: своего URL нет по замыслу
A31: S062 | B31: Комедия на Corn Exchange / Junction / ADC | C31: проверить | D31: Производный (тег «комедия») | G31: своего URL нет по замыслу
A32: S065 | B32: Open Cambridge | C32: да | D32: HTML (curl, пауза 10 с) | E32: https://www.opencambridge.cam.ac.uk/ | F32: https://www.opencambridge.cam.ac.uk/ — 200 через curl; фидов нет | G32: Pantheon отдаёт 403 Python-клиенту httpx, curl — 200
A33: S069 | B33: Cambridge University Botanic Garden | C33: да | D33: HTML | E33: https://www.botanic.cam.ac.uk/whats-on/ | F33: https://www.botanic.cam.ac.uk — 200; alternate-фиды: https://www.botanic.cam.ac.uk/wp-json/oembed/1.0/embed?url=https%3A%2F%2Fwww.botanic.cam.ac.uk%2F, https://www.botanic.cam.ac.uk/wp-json/wp/v2/pages/6; WordPress https://www.botanic.cam.ac.uk/whats-on/ — 200; WordPress
A34: S070 | B34: National Trust: Wimpole, Anglesey Abbey, Wicken Fen | C34: проверить | D34: Ручной сезонный | E34: https://www.nationaltrust.org.uk/visit/cambridgeshire/wimpole-estate/events | F34: https://www.nationaltrust.org.uk/visit/cambridgeshire/wimpole-estate/events — 200 https://www.nationaltrust.org.uk/visit/cambridgeshire/anglesey-abbey-gardens-and-lode-mill/events — 200 https://www.nationaltrust.org.uk/visit/cambridgeshire/wicken-fen-nature-reserve/events — 200 | G34: nationaltrust.org.uk — после 1–2 запросов отдаёт страницу бот-защиты Radware Wicken Fen: /wicken-fen-nature-reserve/events — страница 404; верный адрес не подтверждён
A35: S072 | B35: Cambridge City Council — городские события | C35: да | D35: HTML | E35: https://www.camcityevents.co.uk/events | F35: https://www.cambridge.gov.uk — 200 https://www.cambridge.gov.uk/summer-events — 200 https://www.camcityevents.co.uk/events — 200 | G35: https://www.cambridge.gov.uk/fireworks — 404
A36: S081 | B36: Thriplow Daffodil Weekend | C36: да | D36: HTML | E36: https://www.thriplowdaffodils.org.uk | F36: https://www.thriplowdaffodils.org.uk — 200
A37: S082 | B37: Cambridge Dragon Boat Festival (ACT) | C37: да | D37: HTML | E37: https://act4addenbrookes.org.uk/dragonboat/ | F37: https://act4addenbrookes.org.uk — 200; alternate-фиды: https://act4addenbrookes.org.uk/feed/, https://act4addenbrookes.org.uk/comments/feed/, https://act4addenbrookes.org.uk/wp-json/oembed/1.0/embed?url=https%3A%2F%2Fact4addenbrookes.org.uk%2F; WordPress https://act4addenbrookes.org.uk/events/cambridge-dragon-boat-festival-2026/ — 200; alternate-фиды: https://act4addenbrookes.org.uk/feed/, https://act4addenbrookes.org.uk/comments/feed/, https://act4addenbrookes.org.uk/wp-json/oembed/1.0/embed?url=https%3A%2F%2Fact4addenbrookes.org.uk%2Fevents%2Fcambridge-dragon-boat-festival-2026%2F; WordPress
A38: S087 | B38: The Cambridge Foodies | C38: да | D38: RSS | E38: https://cambridgefoodies.me.uk/feed/ | F38: https://cambridgefoodies.me.uk — 200 в первом проходе, WordPress, alternate RSS /feed/ https://cambridgefoodies.me.uk/feed/ — 200 через HTTP/2 | G38: WordPress.com отвечает 429 при повторных запросах (и HTTP/1.1-клиенту httpx) — нужны HTTP/2, редкие запросы и бэк-офф
A39: S089 | B39: Town and Gown 10k | C39: проверить | D39: Через Cambridge News (S004) и Cambridge 105 (S005) | G39: townandgown10k.com и musculardystrophyuk.org — Cloudflare 403 для любого бот-клиента, включая robots.txt
A40: S090 | B40: DesignMyNight — Cambridge | C40: нет | D40: — (robots.txt запрещает) | E40: https://www.designmynight.com/cambridge | F40: https://www.designmynight.com/cambridge — 200 | G40: robots.txt: Disallow: /cambridge/whats-on и Disallow: /api/ — раздел событий закрыт для роботов разрешённые страницы /cambridge — каталог заведений, событий и JSON-LD Event нет
A41: S091 | B41: Cambridge Live Tickets | C41: да | D41: HTML + JSON-LD | E41: https://www.cambridgelivetickets.co.uk/events | F41: https://www.cambridgelivetickets.co.uk — 200 https://www.cambridgelivetickets.co.uk/events — 200 https://www.cambridgelivetickets.co.uk/events/georgie-carroll-nurse-georgie-carroll-infectious — 200; JSON-LD Event: 1
A42: S092 | B42: Cambridge Independent — News/Business | C42: да | D42: RSS + извлечение Claude | E42: https://www.cambridgeindependent.co.uk/_api/rss/cambridge_independent_business_feed.xml (+ news_feed.xml) | F42: https://www.cambridgeindependent.co.uk/rss-feeds/ — 200 https://www.cambridgeindependent.co.uk/_api/rss/cambridge_independent_business_feed.xml — 200; фид, записей: 20 https://www.cambridgeindependent.co.uk/_api/rss/cambridge_independent_news_feed.xml — 200; фид, записей: 20
A43: S093 | B43: Cambridge News — Food & Drink, Shopping | C43: да | D43: RSS + извлечение Claude | E43: https://www.cambridge-news.co.uk/all-about/food-and-drink?service=rss (+ shopping) | F43: https://www.cambridge-news.co.uk/all-about/food-and-drink — 200; билетная система: ecal https://www.cambridge-news.co.uk/all-about/food-and-drink?service=rss — 200; фид, записей: 4 https://www.cambridge-news.co.uk/all-about/shopping?service=rss — 200; фид, записей: 4
A44: S094 | B44: Grand Arcade — магазины | C44: да | D44: HTML (список магазинов, сравнение) | E44: https://www.grandarcade.co.uk/stores/ | F44: https://www.grandarcade.co.uk/ — 200; alternate-фиды: https://www.grandarcade.co.uk/wp-json/wp/v2/pages/91; WordPress https://www.grandarcade.co.uk/stores/ — 200; alternate-фиды: https://www.grandarcade.co.uk/wp-json/wp/v2/pages/259; WordPress
A45: S095 | B45: Lion Yard — магазины | C45: да | D45: HTML (список магазинов, сравнение) | E45: https://www.thelionyard.co.uk/stores/ | F45: https://www.thelionyard.co.uk/ — 200; alternate-фиды: https://www.thelionyard.co.uk/wp-json/oembed/1.0/embed?url=https%3A%2F%2Fwww.thelionyard.co.uk%2F, https://www.thelionyard.co.uk/wp-json/wp/v2/pages/4; WordPress https://www.thelionyard.co.uk/stores/ — 200; alternate-фиды: https://www.thelionyard.co.uk/./stores/feed/, https://www.thelionyard.co.uk/wp-json/wp/v2/categories/6; WordPress
A46: S096 | B46: The Grafton — магазины | C46: да | D46: HTML (список магазинов, сравнение) | E46: https://graftoncentre.co.uk/stores/ | F46: https://graftoncentre.co.uk/ — 200; alternate-фиды: https://graftoncentre.co.uk/feed/, https://graftoncentre.co.uk/comments/feed/, https://graftoncentre.co.uk/wp-json/oembed/1.0/embed?url=https%3A%2F%2Fgraftoncentre.co.uk%2F; WordPress https://graftoncentre.co.uk/stores/ — 200; alternate-фиды: https://graftoncentre.co.uk/feed/, https://graftoncentre.co.uk/comments/feed/, https://graftoncentre.co.uk/wp-json/oembed/1.0/embed?url=https%3A%2F%2Fgraftoncentre.co.uk%2Fstores%2F; WordPress
A47: S097 | B47: Cambridge BID — новости | C47: да | D47: RSS (без Claude до решения) | E47: https://www.cambridgebid.co.uk/news?format=rss | F47: https://www.cambridgebid.co.uk/news — 200; alternate-фиды: https://www.cambridgebid.co.uk/news?format=rss https://www.cambridgebid.co.uk/news?format=rss — 200; фид, записей: 20

Sheet Контрольные события
A1: ID | B1: Событие | C1: Когда | D1: Где искать | E1: Ключевые слова
A2: C1 | B2: Домашние матчи Cambridge United | C2: весь сезон | D2: S018 (fixtur.es), будущие домашние матчи | E2: Cambridge United
A3: C2 | B3: Mill Road Winter Fair | C3: 2026-12-05 | D3: S038 (сайт ярмарки), Cambridge 105, Cambridge News | E3: Mill Road Winter Fair, Winter Fair
A4: C3 | B4: Town and Gown 10k | C4: октябрь 2026 | D4: через Cambridge News (S004) и Cambridge 105 (S005) — сайт закрыт для ботов | E4: Town and Gown 10, Town & Gown 10, Bidwells Cambridge 10k, Cambridge 10k
A5: C4 | B5: Whittlesea Straw Bear Festival | C5: январь 2027 | D5: Cambridge 105, Visit Cambridge, новости | E5: Straw Bear
A6: C5 | B6: Thriplow Daffodil Weekend | C6: март 2027 | D6: Cambridge 105 | E6: Thriplow, Daffodil Weekend
A7: C6 | B7: Публичные лекции talks.cam | C7: постоянно | D7: S047, списки Major Public Lectures, Darwin College и др. | E7: S047
A8: C7 | B8: Открытия на Mill Road: Catte Latte, Hungarian Soul | C8: уже прошли (архив) | D8: Cambridge Foodies — поток «новое в городе» | E8: Catte Latte, Hungarian Soul
A9: C8 | B9: Cambridge Oktoberfest, Jesus Green | C9: 2026-09-25 – 2026-09-26 | D9: Eventbrite / Skiddle / Ents24 / Cambridge 105 / новости, если ещё видно | E9: Oktoberfest

Sheet Сводка
A1: Категория | B1: Всего источников | C1: Приоритет 1 | D1: URL проверен | E1: Осталось проверить
A2: Сквозные агрегаторы | B2: =COUNTIF(Источники!$B$2:$B$500,A2) | C2: =COUNTIFS(Источники!$B$2:$B$500,A2,Источники!$J$2:$J$500,1) | D2: =COUNTIFS(Источники!$B$2:$B$500,A2,Источники!$K$2:$K$500,"да") | E2: =B2-D2
A3: Концерты | B3: =COUNTIF(Источники!$B$2:$B$500,A3) | C3: =COUNTIFS(Источники!$B$2:$B$500,A3,Источники!$J$2:$J$500,1) | D3: =COUNTIFS(Источники!$B$2:$B$500,A3,Источники!$K$2:$K$500,"да") | E3: =B3-D3
A4: Спорт — смотреть | B4: =COUNTIF(Источники!$B$2:$B$500,A4) | C4: =COUNTIFS(Источники!$B$2:$B$500,A4,Источники!$J$2:$J$500,1) | D4: =COUNTIFS(Источники!$B$2:$B$500,A4,Источники!$K$2:$K$500,"да") | E4: =B4-D4
A5: Спорт — участвовать | B5: =COUNTIF(Источники!$B$2:$B$500,A5) | C5: =COUNTIFS(Источники!$B$2:$B$500,A5,Источники!$J$2:$J$500,1) | D5: =COUNTIFS(Источники!$B$2:$B$500,A5,Источники!$K$2:$K$500,"да") | E5: =B5-D5
A6: Фестивали | B6: =COUNTIF(Источники!$B$2:$B$500,A6) | C6: =COUNTIFS(Источники!$B$2:$B$500,A6,Источники!$J$2:$J$500,1) | D6: =COUNTIFS(Источники!$B$2:$B$500,A6,Источники!$K$2:$K$500,"да") | E6: =B6-D6
A7: Ярмарки | B7: =COUNTIF(Источники!$B$2:$B$500,A7) | C7: =COUNTIFS(Источники!$B$2:$B$500,A7,Источники!$J$2:$J$500,1) | D7: =COUNTIFS(Источники!$B$2:$B$500,A7,Источники!$K$2:$K$500,"да") | E7: =B7-D7
A8: Театр | B8: =COUNTIF(Источники!$B$2:$B$500,A8) | C8: =COUNTIFS(Источники!$B$2:$B$500,A8,Источники!$J$2:$J$500,1) | D8: =COUNTIFS(Источники!$B$2:$B$500,A8,Источники!$K$2:$K$500,"да") | E8: =B8-D8
A9: Кино | B9: =COUNTIF(Источники!$B$2:$B$500,A9) | C9: =COUNTIFS(Источники!$B$2:$B$500,A9,Источники!$J$2:$J$500,1) | D9: =COUNTIFS(Источники!$B$2:$B$500,A9,Источники!$K$2:$K$500,"да") | E9: =B9-D9
A10: Лекции | B10: =COUNTIF(Источники!$B$2:$B$500,A10) | C10: =COUNTIFS(Источники!$B$2:$B$500,A10,Источники!$J$2:$J$500,1) | D10: =COUNTIFS(Источники!$B$2:$B$500,A10,Источники!$K$2:$K$500,"да") | E10: =B10-D10
A11: Выставки и музеи | B11: =COUNTIF(Источники!$B$2:$B$500,A11) | C11: =COUNTIFS(Источники!$B$2:$B$500,A11,Источники!$J$2:$J$500,1) | D11: =COUNTIFS(Источники!$B$2:$B$500,A11,Источники!$K$2:$K$500,"да") | E11: =B11-D11
A12: Детям и семьям | B12: =COUNTIF(Источники!$B$2:$B$500,A12) | C12: =COUNTIFS(Источники!$B$2:$B$500,A12,Источники!$J$2:$J$500,1) | D12: =COUNTIFS(Источники!$B$2:$B$500,A12,Источники!$K$2:$K$500,"да") | E12: =B12-D12
A13: Еда и напитки | B13: =COUNTIF(Источники!$B$2:$B$500,A13) | C13: =COUNTIFS(Источники!$B$2:$B$500,A13,Источники!$J$2:$J$500,1) | D13: =COUNTIFS(Источники!$B$2:$B$500,A13,Источники!$K$2:$K$500,"да") | E13: =B13-D13
... A22: Практическое | B22: =COUNTIF(Источники!$B$2:$B$500,A22) | C22: =COUNTIFS(Источники!$B$2:$B$500,A22,Источники!$J$2:$J$500,1) | D22: =COUNTIFS(Источники!$B$2:$B$500,A22,Источники!$K$2:$K$500,"да") | E22: =B22-D22
A23: Итого | B23: =SUM(B2:B22) | C23: =SUM(C2:C22) | D23: =SUM(D2:D22) | E23: =SUM(E2:E22)

Sheet Схема события
A1: Поле | B1: Тип | C1: Обязательное | D1: Пример | E1: Комментарий
A2: event_id | B2: текст | C2: да | D2: EV-2026-000123 | E2: Внутренний ID
A3: title | B3: текст | C3: да | D3: Cambridge United vs AFC Wimbledon
A4: category | B4: список | C4: да | D4: Спорт — смотреть | E4: Из листа «Категории и теги»
A5: date_start | B5: дата | C5: да | D5: 2026-09-26
A6: time_start | B6: время | C6: да, если известно | D6: 15:00 | E6: Пусто = весь день
A7: date_end | B7: дата | C7: нет | D7: 2026-09-26 | E7: Для многодневных
A8: time_end | B8: время | C8: нет | D8: 17:00
A9: venue_name | B9: текст | C9: да | D9: Abbey Stadium
A10: address | B10: текст | C10: да | D10: Newmarket Road, Cambridge | E10: Точный адрес
A11: postcode | B11: текст | C11: да | D11: (заполнять из источника) | E11: Для карты и расчёта зоны
A12: lat / lon | B12: число | C12: нет | D12: 52.21, 0.15 | E12: Геокодирование по postcode
A13: zone | B13: список | C13: да | D13: Центр | E13: Тег: Центр / до 30 мин / до часа — считается автоматически
A14: price_from | B14: число, £ | C14: нет | D14: 0 | E14: 0 = бесплатно
A15: price_tag | B15: список | C15: да | D15: бесплатно / до £10 / дороже
A16: audience | B16: список (несколько) | C16: нет | D16: дети 5–12; семьи
A17: booking | B17: список | C17: да | D17: без билетов / бронировать / продажа скоро
A18: status | B18: список | C18: да | D18: по плану | E18: по плану / перенесено / отменено / sold out
A19: ticket_url | B19: URL | C19: нет | E19: Здесь партнёрская ссылка, если есть
A20: source_id | B20: ссылка | C20: да | D20: S018 | E20: ID из листа «Источники»
A21: source_url | B21: URL | C21: да | E21: Страница события у первоисточника
A22: description_short | B22: текст | C22: да | E22: 2–3 предложения своими словами (не копировать)
A23: score | B23: число 1–10 | C23: нет | D23: 8 | E23: Оценка LLM «стоит ли внимания»
A24: last_checked | B24: дата-время | C24: да | E24: Когда контур отмен последний раз проверял

Sheet Категории и теги
A1: Ось | B1: Значение
A2: Категория | B2: Концерты
A3: Категория | B3: Спорт — смотреть
A4: Категория | B4: Спорт — участвовать
A5: Категория | B5: Фестивали
A6: Категория | B6: Ярмарки
A7: Категория | B7: Театр
A8: Категория | B8: Кино
A9: Категория | B9: Лекции
A10: Категория | B10: Выставки и музеи
A11: Категория | B11: Детям и семьям
A12: Категория | B12: Еда и напитки
... A39: Статус | B39: sold out

Sheet Проверка P2
A1: ID | B1: Источник | C1: Состояние | D1: Решение | E1: Способ | F1: Endpoint | G1: Примечание
A2: S010 | B2: Peterborough Telegraph | C2: живой | D2: подключён | E2: RSS | F2: https://www.peterboroughtoday.co.uk/rss | G2: RSS (HTML сайта — 403); статьи → извлечение через Claude
A3: S013 | B3: The Portland Arms | C3: закрыт | D3: не нужен | G3: robots.txt отвечает 403; концерты есть на Ents24/Skiddle (S006/S007)
A4: S014 | B4: Storey's Field Centre (Eddington) | C4: живой | D4: не нужен | E4: RSS | F4: https://www.storeysfieldcentre.org.uk/feed/ | G4: фид — 3 новости; события продаются через Eventbrite (S008) и Cambridge Live Tickets (S091)
A5: S015 | B5: West Road Concert Hall | C5: живой | D5: не нужен | E5: HTML | F5: https://www.westroad.org | G5: HTML без JSON-LD; концерты уже приходят из S091, S005, S007, S008
A6: S017 | B6: Saffron Hall | C6: живой | D6: подключён | E6: HTML | F6: https://www.saffronhall.com/ | G6: HTML-карточки: дата, время, наличие билетов (Nearly full → «мало билетов»), отмены
A7: S020 | B7: Cambridge Rugby Club | C7: закрыт | D7: закрыт | G7: страница-проверка (HTTP 202, бот-защита); обходить не будем
A8: S023 | B8: CUCBC — May Bumps / Lent Bumps | C8: живой | D8: ежегодное | E8: RSS | F8: https://www.cucbc.org/rss.xml | G8: Lent/May Bumps — сезонно; RSS новостей есть; даты — через recurring_events
A9: S027 | B9: RunThrough — события в Кембридже | C9: живой | D9: подключён | E9: JSON-LD | F9: https://www.runthrough.co.uk/events-timeline | G9: JSON-LD SportsEvent, но список — 24 ближайших забега по стране; сейчас в регионе 0 (фильтр по почтовым зонам). Ценность низкая — пересмотреть на этапе 6
A10: S029 | B10: Let's Do This — Cambridgeshire | C10: закрыт | D10: закрыт | G10: robots.txt отвечает 403
A11: S034 | B11: Whittlesea Straw Bear Festival | C11: живой | D11: ежегодное | E11: HTML | F11: https://www.strawbear.org.uk | G11: уже в recurring_events (R01)
A12: S035 | B12: Cambridge Film Festival | C12: живой | D12: ежегодное | E12: HTML | F12: https://www.cambridgefilmfestival.org.uk | G12: фестиваль раз в год (осень); HTML без фида — предлагаю добавить в recurring_events
A13: S036 | B13: Cambridge Literary Festival | C13: закрыт | D13: закрыт | G13: 403 на сайт и /events
A14: S044 | B14: Постановки в садах колледжей (лето) | C14: живой | D14: ежегодное | E14: HTML | F14: https://cambridgeshakespeare.com/ | G14: летний сезон постановок; ручной сезонный календарь
A15: S046 | B15: Кино под открытым небом (летние сезоны) | C15: нет событий | D15: ежегодное | E15: HTML | F15: https://www.cambridgefilmfestival.org.uk | G15: летние показы; адрес организатора не подтверждён — ручной сезонный
A16: S049 | B16: Cambridge Union | C16: живой | D16: не нужен | E16: RSS | F16: https://cus.org/feed | G16: мероприятия в основном для членов Union; публичные крупные гости попадают в новости
A17: S051 | B17: Kettle's Yard | C17: живой | D17: подключён | E17: HTML | F17: https://www.kettlesyard.cam.ac.uk/whats-on/ | G17: приоритет 1, коллектора не было: HTML страниц событий (контрольный пример этапа 5)
A18: S053 | B18: IWM Duxford | C18: закрыт | D18: закрыт | G18: iwm.org.uk — 403 (бот-защита) на все страницы; в Ents24/Skiddle Duxford не найден
A19: S054 | B19: Cambridge Science Centre | C19: живой | D19: отложен | E19: RSS | F19: https://www.cambridgesciencecentre.org/whats-on/feed/ | G19: WordPress, тип записей events без дат в API — нужен разбор HTML (детские события — ценно)
A20: S055 | B20: Библиотеки Cambridgeshire | C20: живой | D20: отложен | E20: HTML | F20: https://www.cambridgeshire.gov.uk/residents/libraries-leisure-culture/libraries | G20: Contensis, события библиотек — на сторонних сервисах; нужен разбор
A21: S057 | B21: Eat Cambridge | C21: живой | D21: ежегодное | E21: RSS | F21: https://eat-cambridge.co.uk/feed/ | G21: фестиваль в мае; фид — 3 записи
A22: S058 | B22: Открытия ресторанов | C22: — | D22: не нужен | G22: производный источник: открытия через S092/S093 (извлечение из статей)
A23: S066 | B23: Heritage Open Days | C23: живой | D23: ежегодное | E23: HTML | F23: https://www.heritageopendays.org.uk | G23: Heritage Open Days — сентябрь; поиск по региону в HTML
A24: S067 | B24: National Garden Scheme | C24: живой | D24: отложен | E24: HTML | F24: https://ngs.org.uk | G24: findagarden.ngs.org.uk — сезон весна–лето; разбор HTML
A25: S071 | B25: Ely Cathedral | C25: живой | D25: отложен | E25: HTML | F25: https://www.elycathedral.org | G25: Spektrix без JSON-LD; часть концертов уже из Ents24/Skiddle (S128/S129) и Eventbrite
A26: S075 | B26: Воркшопы в музеях | C26: — | D26: не нужен | G26: производный (музеи)
A27: S076 | B27: Love Mill Road / Mill Road Fringe | C27: живой | D27: отложен | E27: RSS | F27: https://www.millroadwinterfair.org/feed/ | G27: Mill Road Fringe — сезонно; страница WordPress без событийных данных
A28: S077 | B28: Районные FB-группы и Nextdoor | C28: — | D28: не нужен | G28: соцсети — по правилам не парсим
A29: S078 | B29: Перекрытия дорог (county council / one.network) | C29: закрыт | D29: закрыт | G29: robots.txt запрещает
A30: S079 | B30: Greater Anglia / Thameslink / National Rail | C30: живой | D30: не нужен | E30: HTML | F30: https://www.nationalrail.co.uk | G30: не события (транспорт); вернуться к этому, если понадобится практический блок
A31: S083 | B31: «Nihao! China» Cambridge Dragon Boat Festival | C31: живой | D31: ежегодное | E31: JSON-LD | F31: https://www.eventbrite.com/e/nihao-china-cambridge-dragon-boat-festival-2026-tickets-1985873566295 | G31: фестиваль в июне; билеты на Eventbrite (S008)
A32: S084 | B32: Cambridgeshire Cats (американский футбол) | C32: живой | D32: отложен | E32: RSS | F32: https://cambridgeshirecats.com/feed/ | G32: сайт WordPress (новости), страницы расписания нет; сезон BAFA — весна–лето, сейчас матчей нет
A33: S086 | B33: Addenbrooke's Charitable Trust — события | C33: живой | D33: отложен | E33: RSS | F33: https://act4addenbrookes.org.uk/feed/ | G33: WordPress events + RSS; благотворительные забеги и челленджи — разбор HTML
A34: S088 | B34: parkrun — Cambridge, Wimpole и др. | C34: закрыт | D34: закрыт | G34: parkrun.org.uk: robots.txt отвечает 403 — считаем запретом; регулярные забеги — статичный справочник вручную
A35: S098 | B35: South Cambridgeshire District Council | C35: живой | D35: отложен | E35: HTML | F35: https://www.scambs.gov.uk | G35: страница /events есть, событийных данных нет
A36: S099 | B36: East Cambridgeshire District Council | C36: живой | D36: отложен | E36: HTML | F36: https://eastcambs.gov.uk/ | G36: Drupal, /events без структурированных данных
A37: S100 | B37: Huntingdonshire District Council | C37: живой | D37: отложен | E37: HTML | F37: https://www.huntingdonshire.gov.uk | G37: события Hinchingbrooke Country Park — через TicketSource; разбор HTML
A38: S101 | B38: Fenland District Council | C38: закрыт | D38: закрыт | G38: robots.txt отвечает 403
A39: S102 | B39: Peterborough City Council | C39: живой | D39: не нужен | E39: HTML | F39: https://www.peterborough.gov.uk | G39: раздела событий нет (404)
A40: S103 | B40: Ely City Council | C40: закрыт | D40: закрыт | G40: cityofelycouncil.org.uk: robots.txt отвечает 403
A41: S104 | B41: St Ives Town Council | C41: закрыт | D41: закрыт | G41: stivestowncouncil.gov.uk: robots.txt отвечает 403
A42: S105 | B42: St Neots Town Council | C42: живой | D42: отложен | E42: HTML | F42: https://www.stneots-tc.gov.uk | G42: WordPress council_events — разбор HTML
A43: S106 | B43: Huntingdon Town Council | C43: закрыт | D43: закрыт | G43: robots.txt отвечает 403
A44: S107 | B44: Ramsey Town Council | C44: нет событий | D44: не нужен | E44: iCal | F44: https://www.ramseytowncouncil.gov.uk/feeds/ical/638856?nodeid=3007 | G44: iCal совета пуст
A45: S108 | B45: Wisbech Town Council | C45: живой | D45: подключён | E45: iCal | F45: https://www.wisbechtowncouncil.gov.uk/feeds/ical/638856?nodeid=2929 | G45: iCal совета без заседаний: городские события (иллюминация, ярмарки)
A46: S109 | B46: March Town Council | C46: живой | D46: не нужен | E46: RSS | F46: https://www.marchtowncouncil.gov.uk/feed/ | G46: RSS — новости и заседания
A47: S110 | B47: Chatteris Town Council | C47: живой | D47: не нужен | E47: RSS | F47: https://www.chatteristowncouncil.info/feed/ | G47: RSS — новости и заседания
A48: S111 | B48: Whittlesey Town Council | C48: живой | D48: отложен | E48: RSS | F48: https://www.whittleseytowncouncil.gov.uk/feed/ | G48: WordPress, раздел событий — разбор HTML
A49: S112 | B49: Soham Town Council | C49: закрыт | D49: закрыт | G49: soham-tc.gov.uk: robots.txt отвечает 403
A50: S113 | B50: Visit Ely | C50: живой | D50: отложен | E50: RSS | F50: https://www.visitely.org.uk/feed/ | G50: WordPress (API закрыт, 401); события — разбор HTML
A51: S114 | B51: Visit Peterborough | C51: закрыт | D51: закрыт | G51: robots.txt отвечает 403
A52: S115 | B52: Visit Huntingdonshire | C52: живой | D52: отложен | E52: HTML | F52: https://www.discoverhuntingdonshire.co.uk | G52: cPortals, календарь HTML
A53: S116 | B53: Hunts Post | C53: живой | D53: нужно решение | E53: RSS | F53: http://www.huntspost.co.uk/things-to-do/rss/ | G53: RSS /news/rss/ (50 статей, ~неделя); у четырёх газет Newsquest много общих материалов. Извлечение через Claude ≈ 200 статей в неделю ≈ $0.5–0.9/нед (Haiku) — не запускал без вашего решения
A54: S117 | B54: Cambs Times | C54: живой | D54: нужно решение | E54: HTML | F54: https://www.cambstimes.co.uk | G54: RSS /news/rss/ (50 статей, ~неделя); у четырёх газет Newsquest много общих материалов. Извлечение через Claude ≈ 200 статей в неделю ≈ $0.5–0.9/нед (Haiku) — не запускал без вашего решения
A55: S118 | B55: Wisbech Standard | C55: живой | D55: нужно решение | E55: HTML | F55: https://www.wisbechstandard.co.uk | G55: RSS /news/rss/ (50 статей, ~неделя); у четырёх газет Newsquest много общих материалов. Извлечение через Claude ≈ 200 статей в неделю ≈ $0.5–0.9/нед (Haiku) — не запускал без вашего решения
A56: S119 | B56: Ely Standard | C56: живой | D56: нужно решение | E56: HTML | F56: https://www.elystandard.co.uk | G56: RSS /news/rss/ (50 статей, ~неделя); у четырёх газет Newsquest много общих материалов. Извлечение через Claude ≈ 200 статей в неделю ≈ $0.5–0.9/нед (Haiku) — не запускал без вашего решения
A57: S120 | B57: Peterborough Cathedral | C57: закрыт | D57: не нужен | G57: HTTP 202 (бот-защита); концерты собора есть на Ents24/Skiddle (S128/S129)
A58: S121 | B58: Key Theatre (Peterborough) | C58: живой | D58: не нужен | E58: HTML | F58: https://keytheatre-peterborough.com | G58: покрыт Ents24/Skiddle по городу (S128/S129)
A59: S122 | B59: New Theatre Peterborough | C59: живой | D59: не нужен | E59: HTML | F59: https://newtheatre-peterborough.com/ | G59: покрыт Ents24 по городу (S128)
A60: S123 | B60: Peterborough United — домашние матчи | C60: живой | D60: подключён | E60: iCal | F60: https://outlook.live.com/owa/?rru=addsubscription&name=Peterborough+United+FC&url=webcal://ics.fixtur.es/v2/home/peterborough-united-fc.ics | G60: iCal fixtur.es, домашние матчи
A61: S124 | B61: Royston — Town Council / события | C61: живой | D61: не нужен | E61: RSS | F61: https://www.roystontown.uk/feed/ | G61: Royston — через Skiddle/Ents24 по городу (S128/S129)
A62: S125 | B62: Haverhill — Arts Centre / Town Council | C62: живой | D62: не нужен | E62: RSS | F62: https://haverhillartscentre.co.uk/haverhill-arts-centre-homepage/feed/ | G62: Haverhill Arts Centre — через Ents24 по городу (S128)
A63: S126 | B63: Bury St Edmunds — Apex / Theatre Royal / Visit Bury | C63: живой | D63: не нужен | E63: RSS | F63: https://theatreroyal.org/feed/ | G63: Apex и Theatre Royal — через Ents24 по городу (S128)
A64: S127 | B64: Saffron Walden / Newmarket — Town Councils | C64: частично | D64: закрыт | E64: iCal | F64: https://www.newmarket.gov.uk/events/?ical=1 | G64: saffronwalden.gov.uk — 403; newmarket.gov.uk — robots.txt недоступен
A65: S128 | B65: Ents24 — города зоны | C65: живой | D65: подключён | E65: JSON-LD | F65: https://www.ents24.com/whatson/peterborough | G65: Ents24: 12 страниц городов зоны (расширение S006)
A66: S129 | B66: Skiddle — города зоны | C66: живой | D66: подключён | E66: JSON-LD | F66: https://www.skiddle.com/whats-on/Peterborough/ | G66: Skiddle: 12 страниц городов зоны (расширение S007)

Sheet Этап 6
A1: ID | B1: Источник | C1: Блок | D1: Состояние | E1: Решение | F1: Новых уникальных (будущие, в зоне) | G1: Примечание
A2: S001 | B2: Visit Cambridge — events | C2: HTML-источники P1 | D2: живой | E2: подключён | F2: 83 | G2: 7 разделов /event-categories/ (постранично) + страницы событий; раздел family-friendly → категория family
A3: S012 | B3: Cambridge Junction | C3: HTML-источники P1 | D3: живой | E3: подключён | F3: 239 | G3: HTML /whats-on/page/N + страницы событий («Event Information»: дата, время, цена); кэш страниц
A4: S026 | B4: Chariots of Fire | C4: HTML-источники P1 | D4: живой | E4: ежегодное | F4: — | G4: через recurring_events (R11)
A5: S028 | B5: Cambridge Half Marathon | C5: HTML-источники P1 | D5: живой | E5: ежегодное | F5: — | G5: через recurring_events (R03)
A6: S030 | B6: Cambridge Festival (университет) | C6: HTML-источники P1 | D6: живой | E6: ежегодное | F6: — | G6: Cambridge Festival — весна; дата через recurring_events (R04); коллектор программы — перед фестивалем (март)
A7: S031 | B7: Cambridge Folk Festival | C7: HTML-источники P1 | D7: живой | E7: ежегодное | F7: — | G7: через recurring_events (R09)
A8: S041 | B8: Cambridge Arts Theatre | C8: HTML-источники P1 | D8: закрыт | E8: покрыт | F8: — | G8: защита от ботов; афиша — через Ents24 (S006)
A9: S045 | B9: Arts Picturehouse | C9: HTML-источники P1 | D9: живой | E9: не нужен | F9: — | G9: сеансы — только через внутренний AJAX с XSRF-токеном сессии (не используем); обычные сеансы — не события выпуска; спецпоказы приходят через Visit Cambridge, статьи и Cambridge Film Festival (recurring R17)
A10: S048 | B10: University of Cambridge — What's On | C10: HTML-источники P1 | D10: живой | E10: подключён | F10: 41 | G10: недельные страницы admin.cam.ac.uk/whatson (3 недели) + раздел Families; iCal/RSS на webservices закрыты robots.txt — не используем
A11: S052 | B11: University of Cambridge Museums (сводный) | C11: HTML-источники P1 | D11: живой | E11: подключён | F11: 87 | G11: сводная афиша 8 музеев (HTML, один запрос на весь список) + 4 запроса по фильтрам «для кого»/«тип» → категория family по разметке музеев
A12: S056 | B12: Семейные программы музеев | C12: HTML-источники P1 | D12: — | E12: производный | F12: — | G12: тег «дети» из музейных источников — теперь по разметке S052/S048/S001 (категория family) и KIDS_RE
A13: S062 | B13: Комедия на Corn Exchange / Junction / ADC | C13: HTML-источники P1 | D13: — | E13: производный | F13: — | G13: тег «комедия» из S011, S012, S042
A14: S065 | B14: Open Cambridge | C14: HTML-источники P1 | D14: живой | E14: ежегодное | F14: — | G14: через recurring_events (R12)
A15: S069 | B15: Cambridge University Botanic Garden | C15: HTML-источники P1 | D15: живой | E15: подключён | F15: 17 | G15: HTML /whats-on/ + страницы событий; часть событий есть и в S052
A16: S070 | B16: National Trust: Wimpole, Anglesey Abbey, Wicken Fen | C16: HTML-источники P1 | D16: закрыт | E16: вручную | F16: — | G16: National Trust — защита Radware; ручной сезонный календарь
A17: S081 | B17: Thriplow Daffodil Weekend | C17: HTML-источники P1 | D17: живой | E17: ежегодное | F17: — | G17: через recurring_events (R02)
A18: S082 | B18: Cambridge Dragon Boat Festival (ACT) | C18: HTML-источники P1 | D18: живой | E18: ежегодное | F18: — | G18: через recurring_events (R10)
A19: S089 | B19: Town and Gown 10k | C19: HTML-источники P1 | D19: закрыт | E19: ежегодное | F19: — | G19: Cloudflare; через статьи и recurring_events (R14, вручную)
A20: S090 | B20: DesignMyNight — Cambridge | C20: HTML-источники P1 | D20: закрыт | E20: не собираем | F20: — | G20: robots.txt запрещает раздел событий
A21: S054 | B21: Cambridge Science Centre | C21: Семейные источники | D21: живой | E21: подключён | F21: 9 | G21: ссылки — из RSS /whats-on/feed/, дата и время — со страницы события; все события — семейные (family)
A22: S055 | B22: Библиотеки Cambridgeshire | C22: Семейные источники | D22: живой | E22: подключён | F22: 12 | G22: события библиотек — на Eventbrite (страница организатора со страницы совета), JSON-LD страниц событий; серии помечены «recurring series»
A23: S100 | B23: Huntingdonshire District Council | C23: Семейные источники | D23: закрыт | E23: закрыт | F23: — | G23: Hinchingbrooke Country Park: события только на TicketSource (robots.txt отвечает 403 — считаем запретом) и в Facebook (не парсим); страница совета без дат — проверить на этапе 6b через поиск
A24: S130 | B24: Museum of Cambridge | C24: Семейные источники | D24: живой | E24: подключён | F24: 7 | G24: Museum of Cambridge — REST The Events Calendar
A25: S131 | B25: Cambridge Past, Present & Future (Wandlebury, Leper Chapel, Hinxton Watermill…) | C25: Семейные источники | D25: живой | E25: подключён | F25: 106 | G25: Cambridge Past, Present & Future: Wandlebury, Leper Chapel, Hinxton Watermill, Coton, Bourn Windmill, Grantchester — список /events-list/ (Eventin), один запрос
A26: S134 | B26: Centre for Computing History | C26: Семейные источники | D26: живой | E26: подключён | F26: 6 | G26: Centre for Computing History — страница What's On, дата и название в ссылке
A27: S132 | B27: Milton Country Park | C27: Семейные места и аттракционы | D27: живой | E27: подключён | F27: 7 | G27: Milton Country Park (Wix): список /events — название, день, место
A28: S133 | B28: Nene Park / Ferry Meadows | C28: Семейные места и аттракционы | D28: закрыт | E28: отложен | F28: — | G28: Nene Park / Ferry Meadows: при проверке JSON-LD Event на /events/ (24 события), но при сборе сайт начал обрывать соединение и отвечать 403 — защита от ботов, не обходим; коллектор написан (family_misc.NenePark), из прогона убран — повторить позже / этап 6b
A29: S135 | B29: Shepreth Wildlife Park | C29: Семейные места и аттракционы | D29: закрыт | E29: закрыт | F29: — | G29: Shepreth Wildlife Park: сайт отвечает 403 / обрывает соединение — не обходим; этап 6b
A30: S136 | B30: Linton Zoo | C30: Семейные места и аттракционы | D30: живой | E30: не нужен | F30: — | G30: Linton Zoo: на сайте и в DigiTickets — только входные билеты, событий нет; сезонные события — через статьи
A31: S137 | B31: Hamerton Zoo Park | C31: Семейные места и аттракционы | D31: закрыт | E31: закрыт | F31: — | G31: Hamerton Zoo Park: 429 на robots.txt и главную — считаем запретом, повторить на этапе 6b
A32: S138 | B32: Wimpole Home Farm (National Trust) | C32: Семейные места и аттракционы | D32: закрыт | E32: вручную | F32: — | G32: Wimpole Home Farm — National Trust (S070): защита Radware, ручной сезонный календарь
A33: S139 | B33: Audley End House (English Heritage) | C33: Семейные места и аттракционы | D33: живой | E33: отложен | F33: — | G33: Audley End (English Heritage): события на странице загружаются скриптом, в HTML дат нет; JSON-LD нет — этап 6b (поиск) или ручной сезонный календарь
A34: S140 | B34: Woburn Safari Park | C34: Семейные места и аттракционы | D34: живой | E34: отложен | F34: — | G34: Woburn Safari Park: страница событий отвечает 500; вне графства, ~55 км — только события ≥ 7 по правилу 40–60 км
A35: S039 | B35: Рождественские маркеты в центре | C35: Поля, церкви, ярмарки | D35: живой | E35: ежегодное | F35: — | G35: Christmas in Cambridge (Parker's Piece: каток, маркет, колесо) — recurring R21, дата со страницы (13.11.2026 – 3.01.2027)
A36: S071 | B36: Ely Cathedral | C36: Поля, церкви, ярмарки | D36: живой | E36: подключён | F36: 29 | G36: Ely Cathedral: карточки /events (дата + название), один запрос; отложен в P2 на этапе 5
A37: S141 | B37: A Church Near You (Church of England) | C37: Поля, церкви, ярмарки | D37: живой | E37: не нужен | F37: — | G37: A Church Near You: robots.txt разрешает (кроме /christmas/events/), но события — по страницам каждого прихода (сотни в епархии Ely) и в основном регулярные службы; единого источника на графство нет. Концерты крупных церквей уже приходят через Ents24 (King's Chapel, Great St Mary's), University What's On (обеденные концерты GSM) и Visit Cambridge; пропуски — проверить на этапе 6b
A38: S142 | B38: ChurchSuite | C38: Поля, церкви, ярмарки | D38: закрыт | E38: закрыт | F38: — | G38: ChurchSuite: churchsuite.com за Cloudflare (403) — не обходим; календари отдельных приходов (<приход>.churchsuite.com) — если найдутся на этапе 6b
A39: S143 | B39: King's College Chapel | C39: Поля, церкви, ярмарки | D39: живой | E39: покрыт | F39: — | G39: King's College Chapel: страница концертов без дат в HTML; концерты есть в Ents24 (S006) и Visit Cambridge
A40: S144 | B40: St John's College Chapel | C40: Поля, церкви, ярмарки | D40: живой | E40: покрыт | F40: — | G40: St John's College Chapel: события — отдельными страницами без списка с датами; крупные концерты — в Visit Cambridge
A41: S145 | B41: Trinity College Chapel / Great St Mary's | C41: Поля, церкви, ярмарки | D41: закрыт | E41: закрыт | F41: — | G41: Trinity College Chapel: ошибка сертификата TLS; Great St Mary's (gsm.cam.ac.uk — 502, greatstmarys.org — страница на скриптах): обеденные концерты — через University What's On (S048)
A42: S146 | B42: Round Church / St Botolph's | C42: Поля, церкви, ярмарки | D42: живой | E42: не нужен | F42: — | G42: Round Church: сайт визит-центра, событий в афише нет; St Botolph's — домен отвечает 502
A43: S147 | B43: Stourbridge Fair, Big Weekend, включение огней | C43: Поля, церкви, ярмарки | D43: — | E43: ежегодное | F43: — | G43: Stourbridge Fair (Leper Chapel, CPPF) — recurring R22; Big Weekend — R23; включение рождественских огней — R24
A44: S067 | B44: National Garden Scheme | C44: Отложенные P2 | D44: живой | E44: отложен | F44: — | G44: NGS (открытые сады): приложение findagarden на скриптах; сезон апрель–сентябрь — проверить API весной
A45: S076 | B45: Love Mill Road / Mill Road Fringe | C45: Отложенные P2 | D45: живой | E45: отложен | F45: — | G45: Mill Road Fringe: страница без дат, фестиваль летом — проверить к сезону; Winter Fair — в recurring (R16)
A46: S086 | B46: Addenbrooke's Charitable Trust — события | C46: Отложенные P2 | D46: живой | E46: не нужен | F46: — | G46: Addenbrooke's Charitable Trust: благотворительные забеги и акции для участников, не события для зрителей; Dragon Boat Festival — в recurring (R10)
A47: S098 | B47: South Cambridgeshire District Council | C47: Отложенные P2 | D47: живой | E47: не нужен | F47: — | G47: South Cambridgeshire DC: календарь — заседания совета, не публичные события
A48: S099 | B48: East Cambridgeshire District Council | C48: Отложенные P2 | D48: живой | E48: не нужен | F48: — | G48: East Cambridgeshire DC: страница событий пуста
... A50: S111 | B50: Whittlesey Town Council | C50: Отложенные P2 | D50: живой | E50: не нужен | F50: — | G50: Whittlesey Town Council: страницы событий без дат; Straw Bear — в recurring (R01), остальное — статьи Cambs Times (S117)
A51: S113 | B51: Visit Ely | C51: Отложенные P2 | D51: живой | E51: подключён | F51: 10 | G51: Visit Ely: /whats-on/ (JetEngine), дата начала и конца в карточке; площадка не указана — зона по городу Эли
A52: S115 | B52: Visit Huntingdonshire | C52: Отложенные P2 | D52: живой | E52: отложен | F52: — | G52: Discover Huntingdonshire: афиша загружается скриптом, в HTML дат нет — этап 6b (поиск)
A53: S126 | B53: Bury St Edmunds — Apex / Theatre Royal / Visit Bury | C53: Отложенные P2 | D53: живой | E53: подключён | F53: 30 | G53: Theatre Royal Bury St Edmunds: список — REST WordPress /wp-json/wp/v2/events (~33), дата и цена — со страниц спектаклей; RSS /feed/ — новости театра, не афиша
A54: S009 | B54: Songkick — площадки Кембриджа | C54: Источники P3 | D54: живой | E54: не нужен | F54: — | G54: Songkick: страница города — 404, API для новых партнёров закрыт; концерты покрыты Ents24/Skiddle (S006, S007)
A55: S016 | B55: Хоровая музыка колледжей (King's, St John's, Trinity) | C55: Источники P3 | D55: — | E55: не нужен | F55: — | G55: хоровая музыка колледжей — покрыто: King's/GSM через Ents24 и University What's On (S048), St John's/Trinity — Visit Cambridge (S001); регулярный evensong в выпуск не идёт
A56: S019 | B56: Cambridge City FC | C56: Источники P3 | D56: живой | E56: не нужен | F56: — | G56: Cambridge City FC: 8-й уровень (Isthmian North, стадион в Sawston), матчи низкой значимости; сайт лиги без календаря в HTML, Football Web Pages — 403
A57: S022 | B57: Huntingdon Racecourse | C57: Источники P3 | D57: живой | E57: подключён | F57: 11 | G57: Huntingdon Racecourse: JSON-LD на странице событий Jockey Club (как Newmarket S021)
A58: S024 | B58: Town Bumps (Cambridgeshire Rowing Association) | C58: Источники P3 | D58: закрыт | E58: ежегодное | F58: — | G58: Town Bumps: сайт Cambridgeshire Rowing Association отвечает 502; летние Town Bumps — в бэклог recurring (дата вручную)
A59: S025 | B59: Varsity-матчи (Oxford vs Cambridge) | C59: Источники P3 | D59: — | E59: вручную | F59: — | G59: Varsity-матчи: календарь вручную (даты публикуются университетскими клубами), крупные — через статьи
A60: S037 | B60: Cambridge Science Festival / семейные программы | C60: Источники P3 | D60: — | E60: не нужен | F60: — | G60: Cambridge Science Festival слит с Cambridge Festival — дубль R04
A61: S040 | B61: Деревенские fetes и летние ярмарки | C61: Источники P3 | D61: — | E61: покрыт | F61: — | G61: деревенские fetes — через Eventbrite (S008), Visit Cambridge (S001), статьи Newsquest (S116–S119); Facebook-группы не парсим
A62: S043 | B62: Mumford Theatre (ARU) | C62: Источники P3 | D62: живой | E62: подключён | F62: 0 | G62: Mumford Theatre (ARU): афиша на Eventbrite (страница организатора), JSON-LD страниц событий; сейчас у организатора 0 предстоящих (upcomingEventsTotal: 0) — межсезонье
A63: S059 | B63: Cambridge Market (Market Square) | C63: Источники P3 | D63: — | E63: не нужен | F63: — | G63: Cambridge Market — ежедневный рынок, стабильное расписание: справочник, не событие
A64: S060 | B64: All Saints Garden Art & Craft Market | C64: Источники P3 | D64: — | E64: не нужен | F64: — | G64: All Saints Garden Art & Craft Market — регулярный (суббота), справочник
A65: S061 | B65: Car boot sales в округе | C65: Источники P3 | D65: — | E65: не нужен | F65: — | G65: car boot sales — агрегатора с разрешающим robots.txt не нашлось; регулярные — справочник
A66: S063 | B66: Resident Advisor / Skiddle — клубные события | C66: Источники P3 | D66: закрыт | E66: покрыт | F66: — | G66: Resident Advisor — 403; клубные события — Skiddle (S007, S129)
A67: S064 | B67: Квизы в пабах | C67: Источники P3 | D67: — | E67: не нужен | F67: — | G67: квизы в пабах — справочник, не лента событий
A68: S068 | B68: Колледжи — дни открытых дверей и туры | C68: Источники P3 | D68: — | E68: вручную | F68: — | G68: дни открытых дверей колледжей — Open Cambridge (R12) и University What's On (S048)
A69: S073 | B69: Remembrance, Pancake Race и др. традиции | C69: Источники P3 | D69: — | E69: вручную | F69: — | G69: традиции (Remembrance, Pancake Race) — статичный календарь / recurring вручную; Remembrance в Эли — пришло из статьи Ely Standard
A70: S074 | B70: Makespace Cambridge | C70: Источники P3 | D70: закрыт | E70: закрыт | F70: — | G70: Makespace: 429 на robots.txt — считаем запретом; курсы для членов, не публичные события
A71: S080 | B71: Stagecoach East / Park & Ride | C71: Источники P3 | D71: — | E71: не нужен | F71: — | G71: Stagecoach / Park & Ride — транспорт, не события (рубрики «Практическое» в выпуске нет)
A72: S085 | B72: Cambridge Pythons (университетский ам. футбол) | C72: Источники P3 | D72: закрыт | E72: отложен | F72: — | G72: Cambridge Pythons: сайт отвечает 502, сезон BAFA весна–лето — проверить весной вместе с Cambridgeshire Cats (R18)

Sheet Этап 6c
A1: ID | B1: Источник | C1: Состояние | D1: Решение | E1: Событий от источника | F1: Новых уникальных | G1: Новых в окне 1–11.10 | H1: Примечание | I1: Какое прежнее решение было ошибочным и почему
A2: S019 | B2: Cambridge City FC | C2: живой | D2: подключён | E2: 1 | F2: 1 | G2: 1 | H2: Cambridge City FC: домашние матчи из событий сайта клуба (Wix) → «Спорт → Также играют» | I2: S019 (этап 6: «не нужен, матчи низкой значимости») — отменено владельцем проекта после v5
A3: S020 | B3: Cambridge Rugby Club | C3: живой | D3: подключён | E3: 11 | F3: 11 | G3: 1 | H3: Cambridge RUFC: сайт клуба за бот-защитой; с 2026/27 — National League 1 (выбыли из Champ Rugby), весь сезон — PDF лиги (nationalleaguerugby.com) | I3: S020 (этап 5: «закрыт — бот-защита») — календарь нашёлся на сайте лиги
A4: S042 | B4: ADC Theatre | C4: живой | D4: подключён | E4: 28 | F4: 0 | G4: 0 | H4: ADC Theatre: цены — со страницы продажи adctheatre.com (robots.txt отвечает 404 — правил нет)
A5: S045 | B5: Arts Picturehouse | C5: живой | D5: подключён | E5: 5 | F5: 5 | G5: 5 | H5: Arts Picturehouse: страница кинотеатра без AJAX — спецпоказы с датой и «Now Playing»; сеансы (AJAX с XSRF-токеном) не используем | I5: S045 (этап 6: «не нужен») — ошибочно: для рубрики «В кино» нужны спецпоказы и новые фильмы, а не сеансы
A6: S105 | B6: St Neots Town Council | C6: живой | D6: подключён | E6: 18 | F6: 18 | G6: 3 | H6: St Neots Town Council: помесячные страницы council_events → страница события (Date / Location / Time) | I6: S105 (этап 6: «не нужен, 5–6 событий в год») — ошибочно: рынки Farm & Craft дважды в месяц, лекции, прогулки — 18 будущих событий
A7: S144 | B7: St John's College Chapel | C7: живой | D7: подключён | E7: 8 | F7: 8 | G7: 1 | H7: St John's College: joh.cam.ac.uk/festival (лекции, концерты, выставки) + sjcchoir.co.uk/events | I7: S144 (этап 6: «покрыт») — ошибочно: лекционные серии и концерты колледжа не приходят из других источников
A8: S149 | B8: King's College Choir — concerts | C8: живой | D8: подключён | E8: 9 | F8: 5 | G8: 0 | H8: King's College Choir: блок «Upcoming Performances» + страницы концертов (время, программа, «free of charge») | I8: S143 King's College Chapel (этап 6: «покрыт через Ents24/Visit Cambridge») — ошибочно: воскресной органной серии и части концертов там нет; нужен сайт хора
A9: S150 | B9: Cambridge Music (cmp.cam.ac.uk) — West Road, CUMS, колледжи | C9: живой | D9: подключён | E9: 91 | F9: 85 | G9: 4 | H9: cmp.cam.ac.uk: WordPress REST + страницы событий («When / Where»); наборы в студенческие коллективы отсекаются | I9: S015 West Road (этап 5: «не нужен, концерты приходят из S091/S005/S007/S008») — ошибочно: концерты CUMS, факультета и колледжей туда не приходят
A10: S151 | B10: Music Live Cambridge | C10: живой | D10: подключён | E10: 50 | F10: 24 | G10: 14 | H10: Music Live Cambridge: список концертов + iCal каждого (robots.txt разрешает, листинг стабильный)
A11: S152 | B11: Find a Race — забеги в 40 км | C11: живой | D11: подключён | E11: 114 | F11: 110 | G11: 1 | H11: Find a Race: JSON-LD ItemList SportsEvent в радиусе 40 км; виртуальные забеги и «в любой день» не берутся; в выпуске — «Спорт → Поучаствовать» | I11: runabc.co.uk: обрыв соединения на robots.txt — выбран findarace; timeoutdoors.com — 403 (бот-защита)
A12: S153 | B12: Royston Museum | C12: живой | D12: подключён | E12: 18 | F12: 15 | G12: 4 | H12: Royston Museum: страница what-s-on (Wix) — название | дата | цена; TicketTailor закрыт бот-защитой | I12: S124 Royston (этап 5: «через Ents24/Skiddle») — музейные события туда не попадают
A13: S154 | B13: Cambridge United Women | C13: живой | D13: подключён | E13: 8 | F13: 8 | G13: 0 | H13: Cambridge United Women: страница фикстур клуба (FAWNL South East D1, Grange Road)
A14: S155 | B14: Peterborough Phantoms (хоккей, NIHL) | C14: живой | D14: подключён | E14: 25 | F14: 25 | G14: 2 | H14: Peterborough Phantoms (NIHL): страница фикстур клуба gophantoms.co.uk
A15: S163 | B15: Heong Gallery (Downing College) | C15: живой | D15: подключён | E15: 1 | F15: 0 | G15: 0 | H15: Heong Gallery (Downing College): текущая и будущие выставки
A16: S164 | B16: The Women's Art Collection (Murray Edwards) | C16: живой | D16: подключён | E16: 3 | F16: 2 | G16: 0 | H16: The Women's Art Collection (Murray Edwards): выставки и кураторские лекции
A17: S165 | B17: Разбор подборок («Things to do…») | C17: живой | D17: подключён | E17: 0 | F17: 0 | G17: 0 | H17: Разбор подборок («Things to do…»): страница подборки → отдельные события → проверка на их страницах; подборка сама в выпуск не идёт
A18: S084 | B18: Cambridgeshire Cats (американский футбол) | C18: не сезон | D18: не сезон | E18: 0 | F18: 0 | G18: 0 | H18: Cambridgeshire Cats (американский футбол): сезон BAFA весна–лето, в октябре игр нет — подключить к началу сезона
A19: S156 | B19: Vue Cambridge (The Grafton) | C19: закрыт | D19: закрыт | E19: 0 | F19: 0 | G19: 0 | H19: Vue Cambridge: страница 403 (бот-защита)
A20: S157 | B20: Light Cinema Cambridge | C20: закрыт | D20: закрыт | E20: 0 | F20: 0 | G20: 0 | H20: Light Cinema Cambridge: афиша только скриптом
A21: S158 | B21: Saffron Screen | C21: закрыт | D21: закрыт | E21: 0 | F21: 0 | G21: 0 | H21: Saffron Screen: HTTP 202, заглушка бот-защиты
A22: S159 | B22: Babylon Cinema, Ely | C22: закрыт | D22: закрыт | E22: 0 | F22: 0 | G22: 0 | H22: Babylon Cinema (Ely Maltings): обрыв соединения
A23: S160 | B23: CURUFC — университетское регби | C23: закрыт | D23: закрыт | E23: 0 | F23: 0 | G23: 0 | H23: CURUFC (университетское регби, Grange Road): HTTP 202, заглушка
A24: S161 | B24: FA Full-Time | C24: закрыт | D24: закрыт | E24: 0 | F24: 0 | G24: 0 | H24: FA Full-Time: robots.txt 403 (правил нет), страница 403 — бот-защита
A25: S166 | B25: Trinity College events | C25: закрыт | D25: не нужен | E25: 0 | F25: 0 | G25: 0 | H25: Trinity College events: в JSON-LD только встречи выпускников (Лондон, Токио, Нью-Йорк), публичных событий нет

Sheet Монетизация
A1: Продавец | B1: Программа | C1: Сеть | D1: Комиссия | E1: Cookie | F1: Email разрешён | G1: Пометка | H1: Порог выплаты | I1: Источник условий | J1: Дата проверки
A2: Ticketmaster | B2: есть — Ticketmaster Global Affiliate Program | C2: Impact | D2: в официальных материалах не указана: «local commission offering in the individual market contracts within Impact»; сторонние обзоры — 1% от цены билета (не проверено) | E2: не указан официально; сторонние обзоры — 1 день | F2: не указано; условия — в договоре Impact после одобрения | G2: не указано | H2: не указан (Impact) | I2: https://developer.ticketmaster.com/partners/distribution-partners/affiliate-sign-up/ (страница ticketmaster.co.uk/affiliates/ отвечает 403 нашему инструменту) | J2: 2026-09-29
A3: See Tickets | B3: есть — See Tickets UK | C3: Awin (ID 7816) | D3: West End — 5% от номинала без НДС; региональный театр — 2%; достопримечательности и прочие билеты — 1% (без сборов и доставки); не платится за fan-to-fan, пресейлы, события с нулевой комиссией, white-label сайты | E3: 1 день | F3: не видно без входа в Awin | G3: не указано | H3: не видно без входа в Awin | I3: https://ui.awin.com/merchant-profile/7816/commission-groups | J3: 2026-09-29
A4: Eventbrite | B4: есть — Eventbrite Affiliate Program | C4: в условиях не указана (обзоры: impact.com) | D4: в условиях не указана: ставка — в Insertion Order после одобрения; база — сервисный сбор Eventbrite | E4: 7 дней («within seven (7) calendar days») | F4: ограничено: «You may not use Licensed Materials in emails and newsletters unless we provide advance written approval» | G4: обязательная фраза «As an Eventbrite Affiliate, I earn from qualifying ticket purchases…»; ориентир — правила FTC (США) | H4: не указан | I4: https://www.eventbrite.com/help/en-us/articles/328394/eventbrite-affiliate-program-terms-and-conditions/ | J4: 2026-09-29
A5: Skiddle | B5: есть — Skiddle Ticket Affiliate Programme | C5: своя | D5: от 30% выручки Skiddle (сбор 10–15% номинала): ≈10–50 p за билет на клубные вечера, до £4 на крупные события | E5: 30 дней | F5: разрешено: «Sell tickets from your website, newsletters, facebook group, etc» | G5: не указано | H5: порог £25, выплата в конце месяца после события | I5: https://www.skiddle.com/affiliates/ ; https://help.promotioncentre.co.uk/en/articles/9362937-the-skiddle-ticket-affiliate-programme | J5: 2026-09-29
A6: WeGotTickets | B6: есть — WeGotTickets affiliates | C6: своя (RSS/XML-фиды) | D6: не указана («Earn a commission for all sales from your referrals»); заявка через форму | E6: не указан | F6: не указано | G6: не указано | H6: не указан | I6: https://clients.wegottickets.com/affiliates.php | J6: 2026-09-29
A7: Eventim | B7: есть — Eventim UK | C7: Awin (ID 15330) | D7: 1.5% | E7: 30 дней | F7: не видно без входа | G7: не указано | H7: не видно без входа | I7: https://ui.awin.com/merchant-profile/15330 | J7: 2026-09-29
A8: Gigantic | B8: есть (своя страница «Work with us — affiliates»); программа в Paid On Results закрыта | C8: своя | D8: не проверено: официальная страница отвечает 403 нашему инструменту | E8: не проверено | F8: не проверено | G8: не проверено | H8: не проверено | I8: https://workwithus.gigantic.com/work-with-us-affiliates (403) | J8: 2026-09-29
A9: AXS | B9: не подтверждена: UK-программа в каталогах отмечена как истёкшая | C9: Impact (по каталогам) | D9: — | E9: — | F9: — | G9: — | H9: — | I9: официальной страницы программы нет; https://affi.io/m/axs-uk (каталог) | J9: 2026-09-29
A10: DICE | B10: публичной программы нет (страница Partners — для промоутеров и площадок) | C10: — | D10: — | E10: — | F10: — | G10: — | H10: — | I10: https://dice.fm/partners | J10: 2026-09-29
A11: Fatsoma | B11: нет публичной программы: «Reps» — представители, которых нанимает организатор события и сам назначает им комиссию | C11: — | D11: задаёт организатор | E11: — | F11: — | G11: — | H11: — | I11: https://business.fatsoma.com/ticketing/f/reps | J11: 2026-09-29
A12: TicketSource | B12: нет публичной программы: организатор может помечать ссылки своих представителей (?ref=…) для учёта продаж | C12: — | D12: задаёт организатор | E12: — | F12: — | G12: — | H12: — | I12: https://www.ticketsource.co.uk/kb/marketing-and-promotion/reward-affiliates | J12: 2026-09-29
... A23: Клубы (eTicketing / SECUTIX), Planet Ice, IWM, университетские музеи | B23: не найдено | C23: — | D23: — | E23: — | F23: — | G23: — | H23: — | I23: поиск (IWM — только членство и спонсорство) | J23: 2026-09-29
A25: Принципы подключения (зафиксированы на этапе 6d)
A26: Комиссия не влияет на отбор и порядок пунктов выпуска.
A27: Ссылку не менять на другого продавца ради комиссии: партнёрской может быть только ссылка на того же продавца, у которого площадка и так продаёт билеты.
A28: Партнёрские ссылки помечать в письме по правилам ASA/CAP: метка «Ad» (в русской версии — «Реклама») у каждой партнёрской ссылки, до ссылки и заметно; «affiliate» отдельно и «may earn a commission» — недостаточно (https://www.asa.org.uk/advice-online/affiliate-marketing.html). Отдельных указаний по письмам нет — формулировку подтвердить перед подключением.
A29: Программы, где трафик из рассылок запрещён или требует согласия (Eventbrite), — только с письменным разрешением.
A31: Итоги (data/monetization_6d.json)
A32: События окна: 296; продавец определён — 57%; ведут к продавцу с программой — 28% (с учётом важности — 24%)
A33: Пункты v5: 37; к продавцу с программой — 24% (с учётом важности — 23%); где email разрешён — 0%
A34: Пункты v6: 39; к продавцу с программой — 26% (с учётом важности — 24%); где email разрешён — 0%
A35: Пункты v7: 45; к продавцу с программой — 18% (с учётом важности — 15%); где email разрешён — 0%
A36: Доход на 1000 подписчиков в месяц, по пунктам выпуска, low: £0.6 (215 переходов, 4.3 заказов)
A37: Доход на 1000 подписчиков в месяц, по пунктам выпуска, base: £3.1 (430 переходов, 17.2 заказов)
... A41: Доход на 1000 подписчиков в месяц, по событиям окна, high: £11.46 (860 переходов, 51.6 заказов)

Sheet Колледжи
A1: Колледж | B1: Страница публичных событий | C1: Что там | D1: Фид | E1: robots.txt | F1: До: событий за 60 дн. назад / вперёд | G1: После: за 60 дн. назад / вперёд | H1: Источники | I1: Решение
A2: Christ's | B2: christs.cam.ac.uk/events | C2: только встречи выпускников; сады и выставка библиотеки — часы посещения | D2: — | E2: разрешено | F2: 0 / 0 | G2: 0 / 0 | H2: — | I2: публичной афиши нет — не подключаем
A3: Churchill | B3: chu.cam.ac.uk/events/list/ + archives.chu.cam.ac.uk/events/ | C3: лекции Archives Centre (Roskill Lecture), события колледжа, выпускники | D3: iCal, JSON-LD (The Events Calendar) | E3: разрешено | F3: 0 / 2 | G3: 0 / 4 | H3: S008, S150, S169 | I3: подключён S169 (публичные, без выпускников)
A4: Clare | B4: clare.cam.ac.uk/alumni/events | C4: выпускники; концерты хора — на clarecollegechoir.com | D4: — | E4: разрешено | F4: 0 / 2 | G4: 0 / 2 | H4: S008, S048, S150, S170 | I4: концерты — через cmp.cam.ac.uk (S150); сайт хора — обрыв соединения
A5: Clare Hall | B5: clarehall.cam.ac.uk/events/ | C5: лекции (Tanner, Ashby), концерты, выставки | D5: RSS | E5: разрешено | F5: 1 / 2 | G5: 1 / 8 | H5: S048, S150, S170 | I5: подключён S170
A6: Corpus Christi | B6: corpus.cam.ac.uk/events | C6: заглушка Sucuri | D6: — | E6: разрешено | F6: 0 / 2 | G6: 1 / 18 | H6: S008, S150, S168 | I6: закрыт бот-защитой; Corpus Playroom — через Camdram (S168), концерты — S150
A7: Darwin | B7: darwin.cam.ac.uk/lectures | C7: Darwin College Lecture Series (Lent) | D7: — | E7: разрешено | F7: 0 / 0 | G7: 0 / 0 | H7: — | I7: покрыт talks.cam (список 5358, S047)
A8: Downing | B8: dow.cam.ac.uk/about/events | C8: заглушка Sucuri (с перерывами) | D8: — | E8: разрешено | F8: 0 / 0 | G8: 0 / 4 | H8: S067, S168 | I8: Heong Gallery — S163; Howard Theatre — Camdram (S168); сады — NGS (S067)
A9: Emmanuel | B9: emma.cam.ac.uk/members/events | C9: только выпускники (Emmanuel Society) | D9: — | E9: разрешено | F9: 0 / 6 | G9: 0 / 6 | H9: S048, S150 | I9: не подключаем; концерты ECMS — S150
A10: Fitzwilliam | B10: fitz.cam.ac.uk/listing/whats-on | C10: без дат (выпускники) | D10: — | E10: разрешено | F10: 0 / 0 | G10: 0 / 0 | H10: — | I10: публичной афиши нет
A11: Girton | B11: girton.cam.ac.uk/upcoming-events | C11: концерты, лекции; выпускники | D11: — | E11: разрешено | F11: 0 / 1 | G11: 0 / 5 | H11: S150, S174 | I11: подключён S174
A12: Gonville & Caius | B12: cai.cam.ac.uk | C12: заглушка Sucuri; хор — gonvilleandcaiuschoir.com (обрыв) | D12: — | E12: разрешено | F12: 0 / 0 | G12: 0 / 0 | H12: — | I12: закрыт бот-защитой
... A32: Wolfson | B32: wolfson.cam.ac.uk/whats-on | C32: 307 (бот-защита) | D32: — | E32: разрешено | F32: 0 / 5 | G32: 0 / 5 | H32: S131, S150 | I32: закрыт; концерты — S150, лекции CPPF — S131
A34: Покрыто (есть будущие события в базе): до — 19 из 31, после — 22 из 31; свой коллектор — 8; закрыты бот-защитой или обрывом — 13; публичной афиши нет — 7.

Sheet Не разобрано
A1: ID | B1: Источник | C1: URL | D1: Тип проблемы | E1: Подробности | F1: С какой даты | G1: Что теряем | H1: Что делать | I1: Последняя проверка | J1: Статус
A2: C:Clare | B2: Clare — сайт колледжа | C2: https://clarecollegechoir.com/events/category/concerts | D2: обрыв соединения | E2: clarecollegechoir.com: обрыв соединения (tunnel closed) — robots.txt не прочитан | F2: 2026-09-30 | G2: Choir of Clare College — концерты | H2: не обходим; перепроверить позже; публичные события частично приходят из общих источников | I2: 2026-09-30 | J2: открыто
A3: C:Corpus Christi | B3: Corpus Christi — сайт колледжа | C3: https://www.corpus.cam.ac.uk/events | D3: заглушка или проверка бот-защиты | E3: Sucuri: «Please wait while your request is being verified» | F3: 2026-09-30 | G3: Corpus Christi College — события, Parker Library | H3: не обходим; перепроверить позже; публичные события частично приходят из общих источников | I3: 2026-09-30 | J3: открыто
A4: C:Downing | B4: Downing — сайт колледжа | C4: https://www.dow.cam.ac.uk/about/events | D4: заглушка или проверка бот-защиты | E4: Sucuri: страницы событий и садов — заглушка; Heong Gallery открывается | F4: 2026-09-30 | G4: Downing College — события | H4: не обходим; перепроверить позже; публичные события частично приходят из общих источников | I4: 2026-09-30 | J4: открыто
A5: C:Gonville & Caius | B5: Gonville & Caius — сайт колледжа | C5: https://gonvilleandcaiuschoir.com/concerts-broadcasts | D5: заглушка или проверка бот-защиты | E5: Sucuri на cai.cam.ac.uk; gonvilleandcaiuschoir.com — обрыв соединения | F5: 2026-09-30 | G5: Gonville & Caius — события, концерты хора | H5: не обходим; перепроверить позже; публичные события частично приходят из общих источников | I5: 2026-09-30 | J5: открыто
A6: C:Homerton | B6: Homerton — сайт колледжа | C6: https://www.homerton.cam.ac.uk/homerton-life/kate-pretty-lectures | D6: заглушка или проверка бот-защиты | E6: Sucuri: «Please wait while your request is being verified» | F6: 2026-09-30 | G6: Homerton — Kate Pretty Lectures | H6: не обходим; перепроверить позже; публичные события частично приходят из общих источников | I6: 2026-09-30 | J6: открыто
A7: C:Jesus | B7: Jesus — сайт колледжа | C7: https://www.jesus.cam.ac.uk/college/events | D7: заглушка или проверка бот-защиты | E7: 307 на все страницы событий (защита Pantheon/Sucuri) | F7: 2026-09-30 | G7: Jesus College — события, John Hughes Arts Festival | H7: не обходим; перепроверить позже; публичные события частично приходят из общих источников | I7: 2026-09-30 | J7: открыто
A8: C:Murray Edwards | B8: Murray Edwards — сайт колледжа | C8: https://www.murrayedwards.cam.ac.uk/news-events/upcoming-events | D8: заглушка или проверка бот-защиты | E8: Sucuri на страницах событий; Women's Art Collection открывается | F8: 2026-09-30 | G8: Murray Edwards — события | H8: не обходим; перепроверить позже; публичные события частично приходят из общих источников | I8: 2026-09-30 | J8: открыто
A9: C:Pembroke | B9: Pembroke — сайт колледжа | C9: https://pem.cam.ac.uk/college/events/all | D9: заглушка или проверка бот-защиты | E9: 307 на все страницы (защита) | F9: 2026-09-30 | G9: Pembroke — события, Open Doors Festival | H9: не обходим; перепроверить позже; публичные события частично приходят из общих источников | I9: 2026-09-30 | J9: открыто
A10: C:Queens' | B10: Queens' — сайт колледжа | C10: https://queens.cam.ac.uk/about-us/news-events | D10: заглушка или проверка бот-защиты | E10: 202 с заглушкой на все страницы | F10: 2026-09-30 | G10: Queens' College — события | H10: не обходим; перепроверить позже; публичные события частично приходят из общих источников | I10: 2026-09-30 | J10: открыто
A11: C:Sidney Sussex | B11: Sidney Sussex — сайт колледжа | C11: https://www.sid.cam.ac.uk/about-sidney/sidney-greats-lecture-series | D11: заглушка или проверка бот-защиты | E11: Sucuri: «Please wait while your request is being verified» | F11: 2026-09-30 | G11: Sidney Sussex — Sidney Greats lectures | H11: не обходим; перепроверить позже; публичные события частично приходят из общих источников | I11: 2026-09-30 | J11: открыто
A12: C:St Catharine's | B12: St Catharine's — сайт колледжа | C12: https://caths.cam.ac.uk/about-us/college-calendar | D12: заглушка или проверка бот-защиты | E12: 307 на все страницы | F12: 2026-09-30 | G12: St Catharine's — события | H12: не обходим; перепроверить позже; публичные события частично приходят из общих источников | I12: 2026-09-30 | J12: открыто
... A35: S053 | B35: IWM Duxford | C35: https://www.iwm.org.uk/events/iwm-duxford | D35: заглушка или проверка бот-защиты | E35: robots.txt: HTTP 200; страница: 403 | F35: 2026-09-29 | G35: авиашоу и события IWM Duxford | H35: проверить вручную | I35: 2026-09-29 | J35: открыто
A36: S063 | B36: Resident Advisor / Skiddle — клубные события | C36: https://ra.co/events/uk/cambridge | D36: заглушка или проверка бот-защиты | E36: robots.txt: HTTP 200; страница: 403 | F36: 2026-09-29 | H36: проверить вручную | I36: 2026-09-29 | J36: открыто
A37: S088 | B37: parkrun — Cambridge, Wimpole и др. | C37: https://www.parkrun.org.uk/cambridge/ | D37: страница отвечает 403 | E37: robots.txt: HTTP 403 (4xx — правил нет, RFC 9309); страница: 403 | F37: 2026-09-29 | G37: спецзабеги parkrun (Рождество, Новый год) | H37: проверить вручную | I37: 2026-09-29 | J37: открыто
A38: S089 | B38: Town and Gown 10k | C38: https://www.townandgown10k.com/ | D38: страница отвечает 403 | E38: robots.txt: HTTP 403 (4xx — правил нет, RFC 9309); страница: 403 | F38: 2026-09-29 | G38: дата Town & Gown 10K (найдена поиском) | H38: проверить вручную | I38: 2026-09-29 | J38: открыто
A39: S100 | B39: Huntingdonshire District Council | C39: https://www.ticketsource.co.uk/hinchingbrooke-country-park | D39: страница отвечает 403 | E39: robots.txt: HTTP 403 (4xx — правил нет, RFC 9309); страница: 403 | F39: 2026-09-29 | G39: события Hinchingbrooke Country Park (TicketSource) | H39: проверить вручную | I39: 2026-09-29 | J39: открыто
A40: S101 | B40: Fenland District Council | C40: https://www.fenland.gov.uk/events | D40: заглушка или проверка бот-защиты | E40: robots.txt: HTTP 403 (4xx — правил нет, RFC 9309); страница: 403 | F40: 2026-09-29 | H40: проверить вручную | I40: 2026-09-29 | J40: открыто
A41: S103 | B41: Ely City Council | C41: https://www.cityofelycouncil.org.uk/ | D41: заглушка или проверка бот-защиты | E41: robots.txt: HTTP 403 (4xx — правил нет, RFC 9309); страница: 403 | F41: 2026-09-29 | H41: проверить вручную | I41: 2026-09-29 | J41: открыто
A42: S104 | B42: St Ives Town Council | C42: https://www.stivestowncouncil.gov.uk/ | D42: заглушка или проверка бот-защиты | E42: robots.txt: HTTP 403 (4xx — правил нет, RFC 9309); страница: 403 | F42: 2026-09-29 | H42: проверить вручную | I42: 2026-09-29 | J42: открыто
A43: S106 | B43: Huntingdon Town Council | C43: https://www.huntingdontown.gov.uk/council_events/ | D43: заглушка или проверка бот-защиты | E43: robots.txt: HTTP 403 (4xx — правил нет, RFC 9309); страница: 403 | F43: 2026-09-29 | H43: проверить вручную | I43: 2026-09-29 | J43: открыто
A44: S112 | B44: Soham Town Council | C44: https://www.soham-tc.gov.uk/council_events/ | D44: заглушка или проверка бот-защиты | E44: robots.txt: HTTP 403 (4xx — правил нет, RFC 9309); страница: 403 | F44: 2026-09-29 | H44: проверить вручную | I44: 2026-09-29 | J44: открыто
A45: S114 | B45: Visit Peterborough | C45: https://www.visitpeterborough.com/whats-on | D45: заглушка или проверка бот-защиты | E45: robots.txt: HTTP 403 (4xx — правил нет, RFC 9309); страница: 403 | F45: 2026-09-29 | G45: события Питерборо из Visit Peterborough | H45: проверить вручную | I45: 2026-09-29 | J45: открыто
A46: S120 | B46: Peterborough Cathedral | C46: https://peterborough-cathedral.org.uk/whats-on/ | D46: страница отвечает ошибкой | E46: robots.txt: HTTP 200; страница: 404 | F46: 2026-09-29 | G46: концерты собора Питерборо (часть — Ents24/Skiddle) | H46: перепроверить позже | I46: 2026-09-29 | J46: открыто
A47: S127 | B47: Saffron Walden / Newmarket — Town Councils | C47: https://www.saffronwalden.gov.uk/ | D47: заглушка или проверка бот-защиты | E47: robots.txt: HTTP 200; страница: 403 | F47: 2026-09-29 | H47: проверить вручную | I47: 2026-09-29 | J47: открыто
A48: S131 | B48: Cambridge Past, Present & Future | C48: https://cambridgeppf.org/whats-on/ | D48: заглушка или проверка бот-защиты | E48: 30.09 днём нашему боту — страница-заглушка «перезагрузка через 5 секунд» (JS-проверка); утром отдавалась обычная страница. Не обходим. | F48: 2026-09-30 | G48: ~110 событий Wandlebury, Leper Chapel и др. (данные прошлого сбора остаются) | H48: перепроверить в следующем прогоне | I48: 2026-09-30 | J48: открыто
A49: S133 | B49: Nene Park / Ferry Meadows | C49: https://www.nenepark.org.uk/events/ | D49: обрыв соединения | E49: robots.txt: HTTP -1 | F49: 2026-09-29 | G49: события Ferry Meadows / Nene Park | H49: перепроверить позже | I49: 2026-09-29 | J49: открыто
A50: S135 | B50: Shepreth Wildlife Park | C50: https://www.sheprethwildlifepark.co.uk/ | D50: страница отвечает 403 | E50: robots.txt: HTTP 403 (4xx — правил нет, RFC 9309); страница: 403 | F50: 2026-09-29 | G50: события Shepreth Wildlife Park | H50: проверить вручную | I50: 2026-09-29 | J50: открыто
A51: S142 | B51: ChurchSuite | C51: https://churchsuite.com/ | D51: заглушка или проверка бот-защиты | E51: robots.txt: HTTP 200; страница: 403 | F51: 2026-09-29 | G51: календари приходов на ChurchSuite | H51: проверить вручную | I51: 2026-09-29 | J51: открыто
A52: S156 | B52: Vue Cambridge (The Grafton) | C52: https://www.myvue.com/cinema/cambridge/whats-on | D52: заглушка или проверка бот-защиты | E52: robots.txt 200; страница 403 (бот-защита) | F52: 2026-09-29 | G52: новые фильмы и спецпоказы Vue | H52: перепроверить позже; найти поиском | I52: 2026-09-29 | J52: открыто
A53: S157 | B53: Light Cinema Cambridge (Leisure Park) | C53: https://www.thelight.co.uk/cinema/cambridge | D53: страница только на скриптах | E53: страница без текста — афиша только скриптом | F53: 2026-09-29 | G53: новые фильмы и спецпоказы Light | H53: перепроверить позже; найти поиском | I53: 2026-09-29 | J53: открыто
A54: S158 | B54: Saffron Screen (Saffron Walden) | C54: https://www.saffronscreen.com/ | D54: заглушка или проверка бот-защиты | E54: HTTP 202, заглушка бот-защиты | F54: 2026-09-29 | G54: фильмы и спецпоказы Saffron Screen | H54: перепроверить позже; найти поиском | I54: 2026-09-29 | J54: открыто
A55: S159 | B55: Babylon Cinema (Ely Maltings) | C55: https://www.babylonely.co.uk/ | D55: обрыв соединения | E55: robots.txt: обрыв соединения | F55: 2026-09-29 | G55: фильмы Babylon Ely | H55: перепроверить позже; найти поиском | I55: 2026-09-29 | J55: открыто
A56: S160 | B56: CURUFC — Cambridge University Rugby (Grange Road) | C56: https://curufc.com/events-tickets/fixtures/ | D56: заглушка или проверка бот-защиты | E56: HTTP 202, заглушка бот-защиты | F56: 2026-09-29 | G56: матчи университетского регби с публикой | H56: перепроверить позже; найти поиском | I56: 2026-09-29 | J56: открыто
A57: S161 | B57: FA Full-Time (нелиговый и женский футбол) | C57: https://fulltime.thefa.com/ | D57: заглушка или проверка бот-защиты | E57: robots.txt 403 (правил нет), страница 403 | F57: 2026-09-29 | G57: календари нелиговых и женских команд | H57: перепроверить позже; найти поиском | I57: 2026-09-29 | J57: открыто
A58: S162 | B58: Cambridge Kids Club | C58: https://cambridgekidsclub.com/holiday-playschemes/ | D58: заглушка или проверка бот-защиты | E58: Cloudflare challenge (cf-mitigated: challenge) | F58: 2026-09-29 | G58: playscheme на октябрьские каникулы: 9 площадок, 4–11 лет | H58: проверить вручную; запросить у организатора | I58: 2026-09-29 | J58: открыто
A59: P:childcare.admin.cam.ac.uk | B59: University of Cambridge Childcare Office — University Holiday Playscheme | C59: https://www.childcare.admin.cam.ac.uk/university-holiday-playscheme | D59: страница отвечает 403 | E59: страница провайдера открылась | F59: 2026-09-29 | G59: каникулярные программы провайдера | H59: проверить вручную; найти поиском | I59: 2026-09-29 | J59: решено
... A62: P:sport.cam.ac.uk | B62: Sport at Cambridge — children's athletics camps | C62: https://www.sport.cam.ac.uk/childrens-athletic-camps | D62: страница отвечает 403 | E62: страница провайдера открылась | F62: 2026-09-29 | G62: каникулярные программы провайдера | H62: проверить вручную; найти поиском | I62: 2026-09-29 | J62: решено
A63: S019 | B63: Cambridge City FC | C63: https://www.cambridgecityfc.com/fixtures/ | D63: страница отвечает ошибкой | E63: подключён: события на главной cambridgecityfc.com (страница /fixtures/ — 404) | F63: 2026-09-29 | H63: перепроверить позже | I63: 2026-09-29 | J63: решено
A64: S020 | B64: Cambridge Rugby Club | C64: https://www.cambridgerugbyclub.co.uk/fixtures | D64: обрыв соединения | E64: подключён: календарь National League 1 — PDF на nationalleaguerugby.com (сайт клуба закрыт) | F64: 2026-09-29 | G64: домашние матчи Cambridge RUFC | H64: перепроверить позже | I64: 2026-09-29 | J64: решено
